Workbook

Sheet Summary Report

Sheet Data Descriptors 1
O1: RothIRA | U1: Investment income Export | AL1: FRED Graph Observations | AS1: FRED Graph Observations
O2: Monthly | P2: Beginning balance | Q2: Ending balance | R2: Returns | U2: Income For: 237906380 | AL2: Federal Reserve Economic Data, Federal Reserve Bank of St. Louis | AS2: Federal Reserve Economic Data, Federal Reserve Bank of St. Louis
O3: 44866 | P3: 1546.44 | Q3: 1569.76 | R3: =(Q3 - P3) / P3 -> 0.015079796 | U3: Investment income - (Sep-01-2022 - Oct-28-2025) | AL3: Link: https://fred.stlouisfed.org | AS3: Link: https://fred.stlouisfed.org
O4: 44896 | P4: 1569.76 | Q4: 1892.55 | R4: =(Q4 - P4) / P4 -> 0.20563016 | U4: Monthly | V4: Beginning balance | W4: Market change | X4: Dividends | Y4: Interest | Z4: Deposits | AA4: Withdrawals | AB4: Net advisory fees | AC4: Ending balance | AL4: Help: https://fredhelp.stlouisfed.org | AS4: Help: https://fredhelp.stlouisfed.org
O5: 44927 | P5: 1892.55 | Q5: 2115.6 | R5: =(Q5 - P5) / P5 -> 0.11785686 | U5: Oct 2025(As of Oct-28-2025) | V5: 3521.24 | W5: 58.36 | X5: 1.32 | Y5: 0 | Z5: 0 | AA5: 0 | AB5: 0 | AC5: 3581.14 | AD5: Ending balance: $3,580.92 Accrued interest and dividends: $0.22 (not yet paid) | AL5: This data may be copyrighted. Please refer to the Terms of Use: https://fred.stlouisfed.org/legal#fred-terms-faq | AS5: This data may be copyrighted. Please refer to the Terms of Use: https://fred.stlouisfed.org/legal#fred-terms-faq
O6: 44958 | P6: 2115.6 | Q6: 2069.23 | R6: =(Q6 - P6) / P6 -> -0.021918132 | U6: 45901 | V6: 3486.14 | W6: 32.36 | X6: 1.42 | Y6: 0 | Z6: 0 | AA6: 0 | AB6: 0 | AC6: 3521.24 | AD6: Ending balance: $3,519.92 Accrued interest and dividends: $1.32
O7: 44986 | P7: 2069.23 | Q7: 2155.73 | R7: =(Q7 - P7) / P7 -> 0.04180299 | U7: 45870 | V7: 3386.21 | W7: 95.38 | X7: 4.28 | Y7: 0 | Z7: 0 | AA7: 0 | AB7: 0 | AC7: 3486.14 | AD7: Ending balance: $3,485.87 Accrued interest and dividends: $0.27
A8: Roth IRA Returns | C8: 3mo T-Bills % 11/22 - 9/25 | E8: SP500 11/22 - 10/25 | G8: Portfolio Mean Excess Return | I8: S&P 500 1928 - 2024 | K8: 3-month T.Bill 1928 - 2024 | M8: Excess Monthly Returns | O8: 45017 | P8: 2155.73 | Q8: 2186.14 | R8: =(Q8 - P8) / P8 -> 0.01410659 | U8: 45839 | V8: 3482.13 | W8: -98.27 | X8: 2.1 | Y8: 0 | Z8: 0 | AA8: 0 | AB8: 0 | AC8: 3386.21 | AD8: Ending balance: $3,385.96 Accrued interest and dividends: $0.25 | AL8: observation_date | AM8: 3mo T-Bills % Returns | AN8: Monthly Returns | AS8: observation_date | AT8: SP500 | AU8: Monthly Returns | BA8: Historical Sharpe | BB8: Date | BC8: Portfolio Mean Excess Return | BE8: DowJones | BF8: {=_xlfn.STOCKHISTORY("^DJI", EDATE(DATE(2025, 10, 26),-36), TODAY(), 2, 1, 0, 1)} -> Date | BG8: Close | BH8: Returns
O9: 45047 | P9: 2186.14 | Q9: 2212.79 | R9: =(Q9 - P9) / P9 -> 0.012190436 | U9: 45809 | V9: 3536.27 | W9: -56.93 | X9: 1.59 | Y9: 0 | Z9: 0 | AA9: 0 | AB9: 0 | AC9: 3482.13 | AD9: Ending balance: $3,480.93 Accrued interest and dividends: $1.20 | AL9: 44866 | AM9: 4.32 | AN9: =((1 + AM9/100) ^ (1/12)) - 1 -> 0.0035306274 | AS9: 44835 | AT9: 3726.05 | BB9: 44866 | BC9: =R3 - AN9 -> 0.011549169 | BF9: 44835 | BG9: 32732.953
A10: Mean | B10: 0.02479555 | C10: 0.004028336 | E10: 0.016872518 | G10: 0.020989629 | H10: 0.020989629 | I10: 0.11794146 | J10: 0.11794146 | K10: 0.033552896 | L10: 0.033552896 | M10: 0.011162256 | O10: 45078 | P10: 2212.79 | Q10: 2326.05 | R10: =(Q10 - P10) / P10 -> 0.051184252 | U10: 45778 | V10: 3433.57 | W10: 97.86 | X10: 4.52 | Y10: 0 | Z10: 0 | AA10: 0 | AB10: 0 | AC10: 3536.27 | AD10: Ending balance: $3,535.95 Accrued interest and dividends: $0.32 | AL10: 44896 | AM10: 4.36 | AN10: =((1 + AM10/100) ^ (1/12)) - 1 -> 0.0035626875 | AS10: 44866 | AT10: 3917.49 | AU10: =(AT10-AT9)/AT9 -> 0.051378806 | BB10: 44896 | BC10: =R4 - AN10 -> 0.20206747 | BF10: 44866 | BG10: 34589.768 | BH10: =(BG10 - BG9) / BG9 -> 0.056726177
A11: Standard Error | B11: 0.0085101763 | C11: 7.0426164e-05 | E11: 0.0050192622 | G11: 0.008753382 | H11: 0.008753382 | I11: 0.019794105 | J11: 0.019794105 | K11: 0.0030423803 | L11: 0.0030423803 | M11: 0.006086532 | O11: 45108 | P11: 2326.05 | Q11: 2386.7 | R11: =(Q11 - P11) / P11 -> 0.026074246 | U11: 45748 | V11: 3387.16 | W11: 44.25 | X11: 1.89 | Y11: 0 | Z11: 0 | AA11: 0 | AB11: 0 | AC11: 3433.57 | AD11: Ending balance: $3,433.30 Accrued interest and dividends: $0.27 | AL11: 44927 | AM11: 4.69 | AN11: =((1 + AM11/100) ^ (1/12)) - 1 -> 0.0038267548 | AS11: 44896 | AT11: 3912.38 | AU11: =(AT11-AT10)/AT10 -> -0.0013044066 | BB11: 44927 | BC11: =R5 - AN11 -> 0.11403011 | BF11: 44896 | BG11: 33147.249 | BH11: =(BG11 - BG10) / BG10 -> -0.041703662
A12: Median | B12: 0.016045423 | C12: 0.0040103508 | E12: 0.023881732 | G12: 0.011549169 | H12: 0.011549169 | I12: 0.14821092 | J12: 0.14821092 | K12: 0.0299712 | L12: 0.0299712 | M12: 0.018818235 | O12: 45139 | P12: 2386.7 | Q12: 2325.78 | R12: =(Q12 - P12) / P12 -> -0.025524783 | U12: 45717 | V12: 3674.3 | W12: -289.9 | X12: 1.96 | Y12: 0 | Z12: 0 | AA12: 0 | AB12: 0 | AC12: 3387.16 | AD12: Ending balance: $3,386.36 Accrued interest and dividends: $0.80 | AL12: 44958 | AM12: 4.79 | AN12: =((1 + AM12/100) ^ (1/12)) - 1 -> 0.0039066245 | AS12: 44927 | AT12: 3960.66 | AU12: =(AT12-AT11)/AT11 -> 0.012340315 | BB12: 44958 | BC12: =R6 - AN12 -> -0.025824756 | BF12: 44927 | BG12: 34086.037 | BH12: =(BG12 - BG11) / BG11 -> 0.02832175
A13: Mode | B13: #N/A | C13: 0.0044240812 | E13: #N/A | G13: #N/A | H13: #N/A | I13: #N/A | J13: #N/A | K13: 0.0038 | L13: 0.0038 | M13: #N/A | O13: 45170 | P13: 2325.78 | Q13: 2301.77 | R13: =(Q13 - P13) / P13 -> -0.010323418 | U13: 45689 | V13: 3535.45 | W13: 134.13 | X13: 4.06 | Y13: 0 | Z13: 0 | AA13: 0 | AB13: 0 | AC13: 3674.3 | AD13: Ending balance: $3,673.64 Accrued interest and dividends: $0.66 | AL13: 44986 | AM13: 4.86 | AN13: =((1 + AM13/100) ^ (1/12)) - 1 -> 0.0039624918 | AS13: 44958 | AT13: 4079.68 | AU13: =(AT13-AT12)/AT12 -> 0.030050547 | BB13: 44986 | BC13: =R7 - AN13 -> 0.037840498 | BF13: 44958 | BG13: 32656.698 | BH13: =(BG13 - BG12) / BG12 -> -0.041933259
A14: Standard Deviation | B14: 0.051061058 | C14: 0.00041664681 | E14: 0.030115573 | G14: 0.051785706 | H14: 0.051785706 | I14: 0.19494933 | J14: 0.19494933 | K14: 0.029963971 | L14: 0.029963971 | M14: 0.036519192 | O14: 45200 | P14: 2301.77 | Q14: 2267.09 | R14: =(Q14 - P14) / P14 -> -0.015066666 | U14: 45658 | V14: 3393.34 | W14: 139.55 | X14: 2.33 | Y14: 0 | Z14: 0 | AA14: 0 | AB14: 0 | AC14: 3535.45 | AD14: Ending balance: $3,535.22 Accrued interest and dividends: $0.23 | AL14: 45017 | AM14: 5.07 | AN14: =((1 + AM14/100) ^ (1/12)) - 1 -> 0.0041298886 | AS14: 44986 | AT14: 3968.56 | AU14: =(AT14-AT13)/AT13 -> -0.02723743 | BB14: 45017 | BC14: =R8 - AN14 -> 0.0099767017 | BF14: 44986 | BG14: 33274.154 | BH14: =(BG14 - BG13) / BG13 -> 0.018907472
A15: Sample Variance | B15: 0.0026072316 | C15: 1.7359456e-07 | E15: 0.00090694776 | G15: 0.0026817594 | H15: 0.0026817594 | I15: 0.03800524 | J15: 0.03800524 | K15: 0.00089783955 | L15: 0.00089783955 | M15: 0.0013336514 | O15: 45231 | P15: 2267.09 | Q15: 2434.63 | R15: =(Q15 - P15) / P15 -> 0.073900904 | U15: 45627 | V15: 3509.86 | W15: -119.5 | X15: 1.76 | Y15: 0 | Z15: 0 | AA15: 0 | AB15: 0 | AC15: 3393.34 | AD15: Ending balance: $3,392.12 Accrued interest and dividends: $1.22 | AL15: 45047 | AM15: 5.31 | AN15: =((1 + AM15/100) ^ (1/12)) - 1 -> 0.0043208242 | AS15: 45017 | AT15: 4121.47 | AU15: =(AT15-AT14)/AT14 -> 0.038530349 | BB15: 45047 | BC15: =R9 - AN15 -> 0.0078696119 | BF15: 45017 | BG15: 34098.164 | BH15: =(BG15 - BG14) / BG14 -> 0.024764266
A16: Kurtosis | B16: 3.4740854 | C16: -1.7376689 | E16: 0.69584168 | G16: 3.3347884 | H16: 3.3347884 | I16: 0.063145411 | J16: 0.063145411 | K16: 0.94965073 | L16: 0.94965073 | M16: -0.72770661 | O16: 45261 | P16: 2434.63 | Q16: 2647.42 | R16: =(Q16 - P16) / P16 -> 0.087401371 | U16: 45597 | V16: 3254.02 | W16: 251.4 | X16: 4.17 | Y16: 0 | Z16: 0 | AA16: 0 | AB16: 0 | AC16: 3509.86 | AD16: Ending balance: $3,509.59 Accrued interest and dividends: $0.27 | AL16: 45078 | AM16: 5.42 | AN16: =((1 + AM16/100) ^ (1/12)) - 1 -> 0.0044082031 | AS16: 45047 | AT16: 4146.17 | AU16: =(AT16-AT15)/AT15 -> 0.0059930073 | BB16: 45078 | BC16: =R10 - AN16 -> 0.046776048 | BF16: 45047 | BG16: 32908.267 | BH16: =(BG16 - BG15) / BG15 -> -0.034896196
A17: Skewness | B17: 1.2444711 | C17: -0.14071022 | E17: -0.68834978 | G17: 1.2282907 | H17: 1.2282907 | I17: -0.45501636 | J17: -0.45501636 | K17: 1.0164243 | L17: 1.0164243 | M17: -0.14258485 | O17: 45292 | P17: 2647.42 | Q17: 2699.74 | R17: =(Q17 - P17) / P17 -> 0.019762637 | U17: 45566 | V17: 3309.42 | W17: -57.87 | X17: 2.47 | Y17: 0 | Z17: 0 | AA17: 0 | AB17: 0 | AC17: 3254.02 | AD17: Ending balance: $3,254.02 Accrued interest and dividends: $0.00 | AL17: 45108 | AM17: 5.49 | AN17: =((1 + AM17/100) ^ (1/12)) - 1 -> 0.0044637644 | AS17: 45078 | AT17: 4345.37 | AU17: =(AT17-AT16)/AT16 -> 0.04804434 | BB17: 45108 | BC17: =R11 - AN17 -> 0.021610482 | BF17: 45078 | BG17: 34407.6 | BH17: =(BG17 - BG16) / BG16 -> 0.045560967
A18: Range | B18: 0.28377838 | C18: 0.0012210108 | E18: 0.14094833 | G18: 0.28376235 | H18: 0.28376235 | I18: 0.9640087 | J18: 0.9640087 | K18: 0.14003465 | L18: 0.14003465 | M18: 0.1403704 | O18: 45323 | P18: 2699.74 | Q18: 2846.65 | R18: =(Q18 - P18) / P18 -> 0.054416351 | U18: 45536 | V18: 3282.91 | W18: 24.71 | X18: 1.8 | Y18: 0 | Z18: 0 | AA18: 0 | AB18: 0 | AC18: 3309.42 | AD18: Ending balance: $3,309.42 Accrued interest and dividends: $0.00 | AL18: 45139 | AM18: 5.56 | AN18: =((1 + AM18/100) ^ (1/12)) - 1 -> 0.0045192918 | AS18: 45108 | AT18: 4508.08 | AU18: =(AT18-AT17)/AT17 -> 0.037444452 | BB18: 45139 | BC18: =R12 - AN18 -> -0.030044075 | BF18: 45108 | BG18: 35559.533 | BH18: =(BG18 - BG17) / BG17 -> 0.033479037
A19: Minimum | B19: -0.078148219 | C19: 0.0033299958 | E19: -0.058739561 | G19: -0.081694878 | H19: -0.081694878 | I19: -0.43837549 | J19: -0.43837549 | K19: 0.0003272 | L19: 0.0003272 | M19: -0.052691956 | O19: 45352 | P19: 2846.65 | Q19: 2816.97 | R19: =(Q19 - P19) / P19 -> -0.010426291 | U19: 45505 | V19: 3114.82 | W19: 163.7 | X19: 4.39 | Y19: 0 | Z19: 0 | AA19: 0 | AB19: 0 | AC19: 3282.91 | AD19: Ending balance: $3,282.91 Accrued interest and dividends: $0.00 | AL19: 45170 | AM19: 5.56 | AN19: =((1 + AM19/100) ^ (1/12)) - 1 -> 0.0045192918 | AS19: 45139 | AT19: 4457.36 | AU19: =(AT19-AT18)/AT18 -> -0.011250909 | BB19: 45170 | BC19: =R13 - AN19 -> -0.01484271 | BF19: 45139 | BG19: 34721.913 | BH19: =(BG19 - BG18) / BG18 -> -0.023555425
A20: Maximum | B20: 0.20563016 | C20: 0.0045510066 | E20: 0.082208772 | G20: 0.20206747 | H20: 0.20206747 | I20: 0.52563321 | J20: 0.52563321 | K20: 0.14036185 | L20: 0.14036185 | M20: 0.087678441 | O20: 45383 | P20: 2816.97 | Q20: 2744.78 | R20: =(Q20 - P20) / P20 -> -0.025626826 | U20: 45474 | V20: 3116.05 | W20: -3.4 | X20: 2.17 | Y20: 0 | Z20: 0 | AA20: 0 | AB20: 0 | AC20: 3114.82 | AD20: Ending balance: $3,114.82 Accrued interest and dividends: $0.00 | AL20: 45200 | AM20: 5.6 | AN20: =((1 + AM20/100) ^ (1/12)) - 1 -> 0.0045510066 | AS20: 45170 | AT20: 4409.1 | AU20: =(AT20-AT19)/AT19 -> -0.010827037 | BB20: 45200 | BC20: =R14 - AN20 -> -0.019617673 | BF20: 45170 | BG20: 33507.499 | BH20: =(BG20 - BG19) / BG19 -> -0.034975429
A21: Sum | B21: 0.89263981 | C21: 0.14099176 | E21: 0.60741063 | G21: 0.734637 | H21: 0.734637 | I21: 11.440321 | J21: 11.440321 | K21: 3.2546309 | L21: 3.2546309 | M21: 0.40184123 | O21: 45413 | P21: 2744.78 | Q21: 2986.15 | R21: =(Q21 - P21) / P21 -> 0.087937831 | U21: 45444 | V21: 2986.15 | W21: 127.85 | X21: 2.05 | Y21: 0 | Z21: 0 | AA21: 0 | AB21: 0 | AC21: 3116.05 | AD21: Ending balance: $3,116.05 Accrued interest and dividends: $0.00 | AL21: 45231 | AM21: 5.52 | AN21: =((1 + AM21/100) ^ (1/12)) - 1 -> 0.004487566 | AS21: 45200 | AT21: 4269.4 | AU21: =(AT21-AT20)/AT20 -> -0.031684471 | BB21: 45231 | BC21: =R15 - AN21 -> 0.069413338 | BF21: 45200 | BG21: 33052.869 | BH21: =(BG21 - BG20) / BG20 -> -0.013568031
A22: Count | B22: 36 | C22: 35 | E22: 36 | G22: 35 | H22: 35 | I22: 97 | J22: 97 | K22: 97 | L22: 97 | M22: 36 | O22: 45444 | P22: 2986.15 | Q22: 3116.05 | R22: =(Q22 - P22) / P22 -> 0.043500829 | U22: 45413 | V22: 2744.78 | W22: 236.42 | X22: 4.36 | Y22: 0 | Z22: 0 | AA22: 0 | AB22: 0 | AC22: 2986.15 | AD22: Ending balance: $2,985.56 Accrued interest and dividends: $0.59 | AL22: 45261 | AM22: 5.44 | AN22: =((1 + AM22/100) ^ (1/12)) - 1 -> 0.0044240812 | AS22: 45231 | AT22: 4460.06 | AU22: =(AT22-AT21)/AT21 -> 0.044657329 | BB22: 45261 | BC22: =R16 - AN22 -> 0.08297729 | BF22: 45231 | BG22: 35950.893 | BH22: =(BG22 - BG21) / BG21 -> 0.087678441
A23: Confidence Level(95.0%) | B23: 0.017276576 | C23: 0.00014312319 | E23: 0.010189644 | G23: 0.017789013 | H23: 0.017789013 | I23: 0.039290988 | J23: 0.039290988 | K23: 0.0060390771 | L23: 0.0060390771 | M23: 0.012356317 | O23: 45474 | P23: 3116.05 | Q23: 3114.82 | R23: =(Q23 - P23) / P23 -> -0.00039473051 | U23: 45383 | V23: 2816.97 | W23: -76.92 | X23: 2.15 | Y23: 0 | Z23: 0 | AA23: 0 | AB23: 0 | AC23: 2744.78 | AD23: Ending balance: $2,742.20 Accrued interest and dividends: $2.58 | AL23: 45292 | AM23: 5.45 | AN23: =((1 + AM23/100) ^ (1/12)) - 1 -> 0.0044320192 | AS23: 45261 | AT23: 4685.05 | AU23: =(AT23-AT22)/AT22 -> 0.05044551 | BB23: 45292 | BC23: =R17 - AN23 -> 0.015330618 | BF23: 45261 | BG23: 37689.536 | BH23: =(BG23 - BG22) / BG22 -> 0.048361609
O24: 45505 | P24: 3114.82 | Q24: 3282.91 | R24: =(Q24 - P24) / P24 -> 0.053964595 | U24: 45352 | V24: 2846.65 | W24: -32.7 | X24: 2.09 | Y24: 0 | Z24: 0 | AA24: 0 | AB24: 0 | AC24: 2816.97 | AD24: Ending balance: $2,816.04 Accrued interest and dividends: $0.93 | AL24: 45323 | AM24: 5.44 | AN24: =((1 + AM24/100) ^ (1/12)) - 1 -> 0.0044240812 | AS24: 45292 | AT24: 4804.49 | AU24: =(AT24-AT23)/AT23 -> 0.025493858 | BB24: 45323 | BC24: =R18 - AN24 -> 0.04999227 | BF24: 45292 | BG24: 38150.296 | BH24: =(BG24 - BG23) / BG23 -> 0.012225147
O25: 45536 | P25: 3282.91 | Q25: 3309.42 | R25: =(Q25 - P25) / P25 -> 0.0080751528 | U25: 45323 | V25: 2699.74 | W25: 142.35 | X25: 3.95 | Y25: 0 | Z25: 0 | AA25: 0 | AB25: 0 | AC25: 2846.65 | AD25: Ending balance: $2,846.04 Accrued interest and dividends: $0.61 | AL25: 45352 | AM25: 5.47 | AN25: =((1 + AM25/100) ^ (1/12)) - 1 -> 0.0044478932 | AS25: 45323 | AT25: 5011.96 | AU25: =(AT25-AT24)/AT24 -> 0.043182523 | BB25: 45352 | BC25: =R19 - AN25 -> -0.014874184 | BF25: 45323 | BG25: 38996.385 | BH25: =(BG25 - BG24) / BG24 -> 0.022177802
O26: 45566 | P26: 3309.42 | Q26: 3254.02 | R26: =(Q26 - P26) / P26 -> -0.016740093 | U26: 45292 | V26: 2647.42 | W26: 20 | X26: 32.05 | Y26: 0 | Z26: 0 | AA26: 0 | AB26: 0 | AC26: 2699.74 | AD26: Ending balance: $2,699.47 Accrued interest and dividends: $0.27 | AL26: 45383 | AM26: 5.44 | AN26: =((1 + AM26/100) ^ (1/12)) - 1 -> 0.0044240812 | AS26: 45352 | AT26: 5170.57 | AU26: =(AT26-AT25)/AT25 -> 0.031646302 | BB26: 45383 | BC26: =R20 - AN26 -> -0.030050907 | BF26: 45352 | BG26: 39807.374 | BH26: =(BG26 - BG25) / BG25 -> 0.020796517
O27: 45597 | P27: 3254.02 | Q27: 3509.86 | R27: =(Q27 - P27) / P27 -> 0.07862275 | U27: 45261 | V27: 2434.63 | W27: 179.9 | X27: 2.03 | Y27: 0 | Z27: 0 | AA27: 0 | AB27: 0 | AC27: 2647.42 | AD27: Ending balance: $2,616.56 Accrued interest and dividends: $30.86 | AL27: 45413 | AM27: 5.46 | AN27: =((1 + AM27/100) ^ (1/12)) - 1 -> 0.0044399565 | AS27: 45383 | AT27: 5112.49 | AU27: =(AT27-AT26)/AT26 -> -0.011232804 | BB27: 45413 | BC27: =R21 - AN27 -> 0.083497875 | BF27: 45383 | BG27: 37815.916 | BH27: =(BG27 - BG26) / BG26 -> -0.050027376
O28: 45627 | P28: 3509.86 | Q28: 3393.34 | R28: =(Q28 - P28) / P28 -> -0.033197905 | U28: 45231 | V28: 2267.09 | W28: 163.01 | X28: 3.82 | Y28: 0 | Z28: 0 | AA28: 0 | AB28: 0 | AC28: 2434.63 | AD28: Ending balance: $2,433.92 Accrued interest and dividends: $0.71 | AL28: 45444 | AM28: 5.51 | AN28: =((1 + AM28/100) ^ (1/12)) - 1 -> 0.0044796328 | AS28: 45413 | AT28: 5235.23 | AU28: =(AT28-AT27)/AT27 -> 0.024007871 | BB28: 45444 | BC28: =R22 - AN28 -> 0.039021196 | BF28: 45413 | BG28: 38686.322 | BH28: =(BG28 - BG27) / BG27 -> 0.02301692
O29: 45658 | P29: 3393.34 | Q29: 3535.45 | R29: =(Q29 - P29) / P29 -> 0.041879093 | U29: 45200 | V29: 2301.77 | W29: -36.93 | X29: 2 | Y29: 0 | Z29: 0 | AA29: 0 | AB29: 0 | AC29: 2267.09 | AD29: Ending balance: $2,266.84 Accrued interest and dividends: $0.25 | AL29: 45474 | AM29: 5.43 | AN29: =((1 + AM29/100) ^ (1/12)) - 1 -> 0.0044161425 | AS29: 45444 | AT29: 5415.14 | AU29: =(AT29-AT28)/AT28 -> 0.034365252 | BB29: 45474 | BC29: =R23 - AN29 -> -0.004810873 | BF29: 45444 | BG29: 39118.864 | BH29: =(BG29 - BG28) / BG28 -> 0.011180755
O30: 45689 | P30: 3535.45 | Q30: 3674.3 | R30: =(Q30 - P30) / P30 -> 0.039273643 | U30: 45170 | V30: 2325.78 | W30: -28.71 | X30: 3.78 | Y30: 0 | Z30: 0 | AA30: 0 | AB30: 0 | AC30: 2301.77 | AD30: Ending balance: $2,300.85 Accrued interest and dividends: $0.92 | AL30: 45505 | AM30: 5.3 | AN30: =((1 + AM30/100) ^ (1/12)) - 1 -> 0.0043128766 | AS30: 45474 | AT30: 5538 | AU30: =(AT30-AT29)/AT29 -> 0.022688241 | BB30: 45505 | BC30: =R24 - AN30 -> 0.049651719 | BF30: 45474 | BG30: 40842.792 | BH30: =(BG30 - BG29) / BG29 -> 0.044068971
O31: 45717 | P31: 3674.3 | Q31: 3387.16 | R31: =(Q31 - P31) / P31 -> -0.078148219 | U31: 45139 | V31: 2386.7 | W31: -65.33 | X31: 1.86 | Y31: 0 | Z31: 0 | AA31: 0 | AB31: 0 | AC31: 2325.78 | AD31: Ending balance: $2,323.23 Accrued interest and dividends: $2.55 | AL31: 45536 | AM31: 4.92 | AN31: =((1 + AM31/100) ^ (1/12)) - 1 -> 0.0040103508 | AS31: 45505 | AT31: 5478.21 | AU31: =(AT31-AT30)/AT30 -> -0.010796316 | BB31: 45536 | BC31: =R25 - AN31 -> 0.0040648021 | BF31: 45505 | BG31: 41563.08 | BH31: =(BG31 - BG30) / BG30 -> 0.017635614
O32: 45748 | P32: 3387.16 | Q32: 3433.57 | R32: =(Q32 - P32) / P32 -> 0.013701744 | U32: 45108 | V32: 2326.05 | W32: 58.54 | X32: 1.78 | Y32: 0 | Z32: 0 | AA32: 0 | AB32: 0 | AC32: 2386.7 | AD32: Ending balance: $2,386.37 Accrued interest and dividends: $0.33 | AL32: 45566 | AM32: 4.72 | AN32: =((1 + AM32/100) ^ (1/12)) - 1 -> 0.003850723 | AS32: 45536 | AT32: 5621.26 | AU32: =(AT32-AT31)/AT31 -> 0.026112544 | BB32: 45566 | BC32: =R26 - AN32 -> -0.020590816 | BF32: 45536 | BG32: 42330.15 | BH32: =(BG32 - BG31) / BG31 -> 0.018455562
O33: 45778 | P33: 3433.57 | Q33: 3536.27 | R33: =(Q33 - P33) / P33 -> 0.02991056 | U33: 45078 | V33: 2212.79 | W33: 110.56 | X33: 1.92 | Y33: 0 | Z33: 0 | AA33: 0 | AB33: 0 | AC33: 2326.05 | AD33: Ending balance: $2,325.27 Accrued interest and dividends: $0.78 | AL33: 45597 | AM33: 4.62 | AN33: =((1 + AM33/100) ^ (1/12)) - 1 -> 0.0037708043 | AS33: 45566 | AT33: 5792.32 | AU33: =(AT33-AT32)/AT32 -> 0.0304309 | BB33: 45597 | BC33: =R27 - AN33 -> 0.074851945 | BF33: 45566 | BG33: 41763.46 | BH33: =(BG33 - BG32) / BG32 -> -0.013387385
O34: 45809 | P34: 3536.27 | Q34: 3482.13 | R34: =(Q34 - P34) / P34 -> -0.015309917 | U34: 45047 | V34: 2186.14 | W34: 22.19 | X34: 3.67 | Y34: 0 | Z34: 0 | AA34: 0 | AB34: 0 | AC34: 2212.79 | AD34: Ending balance: $2,212.00 Accrued interest and dividends: $0.79 | AL34: 45627 | AM34: 4.39 | AN34: =((1 + AM34/100) ^ (1/12)) - 1 -> 0.0035867252 | AS34: 45597 | AT34: 5929.92 | AU34: =(AT34-AT33)/AT33 -> 0.023755594 | BB34: 45627 | BC34: =R28 - AN34 -> -0.036784631 | BF34: 45597 | BG34: 44910.65 | BH34: =(BG34 - BG33) / BG33 -> 0.075357502
O35: 45839 | P35: 3482.13 | Q35: 3386.21 | R35: =(Q35 - P35) / P35 -> -0.027546358 | U35: 45017 | V35: 2155.73 | W35: 28.49 | X35: 1.74 | Y35: 0 | Z35: 0 | AA35: 0 | AB35: 0 | AC35: 2186.14 | AD35: Ending balance: $2,185.96 Accrued interest and dividends: $0.18 | AL35: 45658 | AM35: 4.34 | AN35: =((1 + AM35/100) ^ (1/12)) - 1 -> 0.0035466589 | AS35: 45627 | AT35: 6010.91 | AU35: =(AT35-AT34)/AT34 -> 0.013657857 | BB35: 45658 | BC35: =R29 - AN35 -> 0.038332434 | BF35: 45627 | BG35: 42544.22 | BH35: =(BG35 - BG34) / BG34 -> -0.052691956
... O37: 45901 | P37: 3486.14 | Q37: 3521.24 | R37: =(Q37 - P37) / P37 -> 0.010068442 | U37: 44958 | V37: 2115.6 | W37: -50.22 | X37: 3.3 | Y37: 0 | Z37: 0 | AA37: 0 | AB37: 0 | AC37: 2069.23 | AD37: Ending balance: $2,068.68 Accrued interest and dividends: $0.55 | AL37: 45717 | AM37: 4.34 | AN37: =((1 + AM37/100) ^ (1/12)) - 1 -> 0.0035466589 | AS37: 45689 | AT37: 6038.69 | AU37: =(AT37-AT36)/AT36 -> 0.0098954431 | BB37: 45717 | BC37: =R31 - AN37 -> -0.081694878 | BF37: 45689 | BG37: 43840.91 | BH37: =(BG37 - BG36) / BG36 -> -0.015798751
O38: As of Oct-28-2025 | P38: 3521.24 | Q38: 3581.14 | R38: 0.01701105 | U38: 44927 | V38: 1892.55 | W38: 221.36 | X38: 1.41 | Y38: 0 | Z38: 0 | AA38: 0 | AB38: 0 | AC38: 2115.6 | AD38: Ending balance: $2,115.32 Accrued interest and dividends: $0.28 | AL38: 45748 | AM38: 4.32 | AN38: =((1 + AM38/100) ^ (1/12)) - 1 -> 0.0035306274 | AS38: 45717 | AT38: 5683.98 | AU38: =(AT38-AT37)/AT37 -> -0.058739561 | BB38: 45748 | BC38: =R32 - AN38 -> 0.010171117 | BF38: 45717 | BG38: 42001.76 | BH38: =(BG38 - BG37) / BG37 -> -0.041950543
U39: 44896 | V39: 1569.76 | W39: -74.31 | X39: 3.21 | Y39: 0 | Z39: 393.14 | AA39: 0 | AB39: 0 | AC39: 1892.55 | AD39: Ending balance: $1,891.80 Accrued interest and dividends: $0.75 | AL39: 45778 | AM39: 4.36 | AN39: =((1 + AM39/100) ^ (1/12)) - 1 -> 0.0035626875 | AS39: 45748 | AT39: 5369.5 | AU39: =(AT39-AT38)/AT38 -> -0.055327429 | BB39: 45778 | BC39: =R33 - AN39 -> 0.026347872 | BF39: 45748 | BG39: 40669.36 | BH39: =(BG39 - BG38) / BG38 -> -0.03172248
U40: 44866 | V40: 1546.44 | W40: 20.08 | X40: 2.56 | Y40: 0 | Z40: 0 | AA40: 0 | AB40: 0 | AC40: 1569.76 | AD40: Ending balance: $1,569.08 Accrued interest and dividends: $0.68 | AL40: 45809 | AM40: 4.42 | AN40: =((1 + AM40/100) ^ (1/12)) - 1 -> 0.0036107566 | AS40: 45778 | AT40: 5810.92 | AU40: =(AT40-AT39)/AT39 -> 0.082208772 | BB40: 45809 | BC40: =R34 - AN40 -> -0.018920674 | BF40: 45778 | BG40: 42270.07 | BH40: =(BG40 - BG39) / BG39 -> 0.039359115
U41: 44835 | V41: 490.41 | W41: 53.99 | X41: 1.86 | Y41: 0 | Z41: 1000 | AA41: 0 | AB41: 0 | AC41: 1546.44 | AD41: Ending balance: $1,546.26 Accrued interest and dividends: $0.18 | AL41: 45839 | AM41: 4.41 | AN41: =((1 + AM41/100) ^ (1/12)) - 1 -> 0.0036027469 | AS41: 45809 | AT41: 6029.95 | AU41: =(AT41-AT40)/AT40 -> 0.037692827 | BB41: 45839 | BC41: =R35 - AN41 -> -0.031149105 | BF41: 45809 | BG41: 44094.77 | BH41: =(BG41 - BG40) / BG40 -> 0.04316766
U42: Sep 2022(As of Sep-01-2022) | V42: 0 | W42: -9.66 | X42: 0.07 | Y42: 0 | Z42: 500 | AA42: 0 | AB42: 0 | AC42: 490.41 | AD42: Ending balance: $490.41 Accrued interest and dividends: $0.00 | AL42: 45870 | AM42: 4.3 | AN42: =((1 + AM42/100) ^ (1/12)) - 1 -> 0.0035145931 | AS42: 45839 | AT42: 6296.5 | AU42: =(AT42-AT41)/AT41 -> 0.044204347 | BB42: 45870 | BC42: =R36 - AN42 -> 0.025996276 | BF42: 45839 | BG42: 44130.98 | BH42: =(BG42 - BG41) / BG41 -> 0.00082118582
U43: Total | X43: 125.51 | Y43: 0 | Z43: 1893.14 | AA43: 0 | AB43: 0 | AL43: 45901 | AM43: 4.07 | AN43: =((1 + AM43/100) ^ (1/12)) - 1 -> 0.0033299958 | AS43: 45870 | AT43: 6408.95 | AU43: =(AT43-AT42)/AT42 -> 0.017859128 | BB43: 45901 | BC43: =R37 - AN43 -> 0.0067384467 | BF43: 45870 | BG43: 45544.88 | BH43: =(BG43 - BG42) / BG42 -> 0.032038717
U44: Total Dividends, Interest and Market Change(Minus fees)$1,688.00 | V44: Total Deposits and Withdrawals$1,893.14 | W44: Average total income$3.31 | AS44: 45901 | AT44: 6584.02 | AU44: =(AT44-AT43)/AT43 -> 0.027316487 | BF44: 45901 | BG44: 46397.89 | BH44: =(BG44 - BG43) / BG43 -> 0.018728999
AS45: 45931 | AT45: 6700.1 | AU45: =(AT45-AT44)/AT44 -> 0.017630566 | BF45: 45931 | BG45: 47706.37 | BH45: =(BG45 - BG44) / BG44 -> 0.028201282
U46: For existing accounts, deposit values for each period represent a total of all of the deposits in the account or portfolio within that same period. Initial deposits for new accounts are
U47: included in the Beginning Balance in the month following the initial deposit (e.g., a deposit made on January 15 would be captured in the Beginning Balance in February). For accounts
U48: opened prior to July 1, 2020, the initial deposit is based on the market value at the beginning of the first full month in cases where the actual amount deposited in the account is
U49: unavailable for reporting. The purchase of foreign currency is treated as a withdrawal from the account, and the sale of foreign currency is treated as a deposit into the account.
U50: Additionally, foreign currency positions are excluded from the total market value and dividends paid in foreign currencies are not reflected in the dividend income. The net advisory
U51: fees are calculated by subtracting the applicable credit amount from the gross advisory fee (or discounted gross advisory fee, as applicable). Please note that your net advisory fee
U52: does not include any additional fees and credits or fees associated with the underlying investments held in your account. If you paid your Quarterly Advisory Fee by check or from
U53: funds outside your account, payment is shown as Deposits in Total Deposits/Withdrawals. On summary view, account balance and income details reflect values from the start of the
U54: period specified through the previous day's close of business. Accrued interest and accrued dividends represent income to be paid as of the end of the time period represented. Once
U55: paid, these amounts will be shown as interest and dividends. On the detail view, a timeframe selector and frequency options are available to change the investment income details
U56: shown. Interest and dividends for each period are shown. Market Change represents the change in your account due to investment activity, exclusive of interest, dividends, deposits,
U57: and withdrawals. Please note we do not record transactions of deposits and withdrawals, of the same amount, on the same day, within the same account in this experience. To view
... U61: 1132521.4.0

Sheet Data Descriptors 2
A1: Date updated: | B1: 45658
A2: Created by: | B2: Aswath Damodaran, adamodar@stern.nyu.edu
A3: What is this data? | B3: Historical returns: Stocks, Bonds & T.Bills with premiums | I3: In US Dollars
A4: Home Page: | B4: https://pages.stern.nyu.edu/~adamodar/
A5: Data website: | B5: https://pages.stern.nyu.edu/~adamodar/New_Home_Page/data.html
A6: Companies in each industry: | B6: https://pages.stern.nyu.edu/~adamodar/pc/datasets/indname.xls
A7: Variable definitions: | B7: https://pages.stern.nyu.edu/~adamodar/New_Home_Page/datafile/variable.htm
A8: Customized Geometric risk premium estimator
A9: What is your riskfree rate? | D9: LT | G9: Estimates of risk premiums from 1928, over the last 50 years and over the last 10 years
A10: Enter your starting year | D10: 2014
A12: Value of stocks in starting year: | E12: =IF(D10=1928,100,VLOOKUP(D10-1,A21:O117,9)) -> 255553.31
A13: Value of T.Bills in starting year: | E13: =IF(D10=1928,100,VLOOKUP(D10-1,A21:L117,11)) -> 1982.0113
A14: Value of T.bonds in starting year: | E14: =IF(D10=1928,100,VLOOKUP(D10-1,A20:L117,12)) -> 6295.7854
A15: Value of Real estate in starting year | E15: =IF(D10=1928,100,VLOOKUP(D10-1,A20:N117,14)) -> 2728.3897
A16: Value of Gold in starting year | E16: =IF(D10=1928,100,VLOOKUP(D10-1,A20:O117,15)) -> 5835.7558
A17: Estimate of risk premium based on your inputs: | E17: =IF(D9="ST",(I117/E12)^(1/(A117-D10+1))-(K117/E13)^(1/(A117-D10+1)),(I117/E12)^(1/(A117-D10+1))-(L117/E14)^(1/(A117-D10+1))) -> 0.11851184
B19: Annual Returns on Investments in | I19: Value of $100 invested at start of 1928 in | P19: Annual Risk Premium | U19: Annual Real Returns | AC19: Value of $100 invested at start of 1928 in real terms | AJ19: Real Risk Premium
A20: Year | B20: S&P 500 (includes dividends) | C20: US Small cap (bottom decile) | D20: 3-month T.Bill | E20: US T. Bond (10-year) | F20: Baa Corporate Bond | G20: Real Estate | H20: Gold* | I20: S&P 500 (includes dividends)3 | J20: US Small cap (bottom decile) Cum Value | K20: 3-month T.Bill4 | L20: US T. Bond5 | M20: Baa Corporate Bond2 | N20: Real Estate2 | O20: Gold2 | P20: Stocks - Bills | Q20: Stocks - Bonds | R20: Small Cap Premium (S&P 500 minus Bottom Decile) | S20: Stocks - Baa Corp Bond | T20: Historical ERP | U20: Inflation Rate | V20: S&P 500 (includes dividends)2 | W20: US Small cap (bottom decile)22 | X20: 3-month T. Bill (Real) | Y20: !0-year T.Bonds | Z20: Baa Corp Bonds | AA20: Real Estate3 | AB20: Gold | AC20: S&P 500 (includes dividends)3 | AD20: US Small cap (bottom decile)22 | AE20: 3-month T.Bill4 | AF20: US T. Bond5 | AG20: Baa Corporate Bond2 | AH20: Real Estate2 | AI20: Gold2 | AJ20: Stocks minus T. Bills | AK20: Stocks minus T.Bonds
A21: 1928 | B21: =('[1]S&P 500 & Raw Data'!B4-'[1]S&P 500 & Raw Data'!B3+'[1]S&P 500 & Raw Data'!C4)/'[1]S&P 500 & Raw Data'!B3 -> 0.43811155 | C21: ='[1]Small Cap'!B2 -> 0.5991 | D21: 0.0308 | E21: ='[1]S&P 500 & Raw Data'!F4 -> 0.0083547086 | F21: ='[1]S&P 500 & Raw Data'!J4 -> 0.032195515 | G21: ='[1]Home Prices'!B4/'[1]Home Prices'!B3-1 -> 0.014910537 | H21: ='[1]Gold Prices'!B3/'[1]Gold Prices'!B2-1 -> 0.00096899225 | I21: =100*(1+B21) -> 143.81116 | J21: 159.91 | K21: =100*(1+D21) -> 103.08 | L21: =100*(1+E21) -> 100.83547 | M21: =100*(1+F21) -> 103.21955 | N21: =100*(1+G21) -> 101.49105 | O21: =100*(1+H21) -> 100.0969 | P21: =B21-D21 -> 0.40731155 | Q21: =B21-E21 -> 0.42975684 | R21: ='Data Descriptors 2'!$C21-'Data Descriptors 2'!$B21 -> 0.16098845 | S21: =B21-F21 -> 0.40591604 | U21: ='[1]Inflation Rate'!C26 -> -0.0115607 | V21: =(1+B21)/(1+$U21)-1 -> 0.45493158 | W21: =(1+C21)/(1+$U21)-1 -> 0.61780293 | X21: =(1+D21)/(1+$U21)-1 -> 0.042856147 | Y21: =(1+E21)/(1+$U21)-1 -> 0.020148337 | Z21: =(1+F21)/(1+$U21)-1 -> 0.044267984 | AA21: =(1+G21)/(1+$U21)-1 -> 0.026780842 | AB21: =(1+H21)/(1+$U21)-1 -> 0.012676238 | AC21: =100*(1+V21) -> 145.49316 | AD21: =100*(1+W21) -> 161.78029 | AE21: =100*(1+X21) -> 104.28561 | AF21: =100*(1+Y21) -> 102.01483 | AG21: =100*(1+Z21) -> 104.4268 | AH21: =100*(1+AA21) -> 102.67808 | AI21: =100*(1+AB21) -> 101.26762 | AJ21: ='Data Descriptors 2'!$V21-'Data Descriptors 2'!$X21 -> 0.41207543 | AK21: ='Data Descriptors 2'!$V21-'Data Descriptors 2'!$Y21 -> 0.43478324
A22: 1929 | B22: =('[1]S&P 500 & Raw Data'!B5-'[1]S&P 500 & Raw Data'!B4+'[1]S&P 500 & Raw Data'!C5)/'[1]S&P 500 & Raw Data'!B4 -> -0.082979466 | C22: ='[1]Small Cap'!B3 -> -0.4661 | D22: 0.0316 | E22: ='[1]S&P 500 & Raw Data'!F5 -> 0.042038042 | F22: ='[1]S&P 500 & Raw Data'!J5 -> 0.030178562 | G22: ='[1]Home Prices'!B5/'[1]Home Prices'!B4-1 -> -0.020568071 | H22: ='[1]Gold Prices'!B4/'[1]Gold Prices'!B3-1 -> -0.0014520813 | I22: =I21*(1+B22) -> 131.87778 | J22: =J21*(1+C22) -> 85.375949 | K22: =K21*(1+D22) -> 106.33733 | L22: =L21*(1+E22) -> 105.0744 | M22: =M21*(1+F22) -> 106.33457 | N22: =N21*(1+G22) -> 99.403579 | O22: =O21*(1+H22) -> 99.95155 | P22: =B22-D22 -> -0.11457947 | Q22: =B22-E22 -> -0.12501751 | R22: ='Data Descriptors 2'!$C22-'Data Descriptors 2'!$B22 -> -0.38312053 | S22: =B22-F22 -> -0.11315803 | U22: ='[1]Inflation Rate'!C27 -> 0.005848 | V22: =(1+B22)/(1+$U22)-1 -> -0.088311023 | W22: =(1+C22)/(1+$U22)-1 -> -0.46920409 | X22: =(1+D22)/(1+$U22)-1 -> 0.025602278 | Y22: =(1+E22)/(1+$U22)-1 -> 0.035979633 | Z22: =(1+F22)/(1+$U22)-1 -> 0.024189105 | AA22: =(1+G22)/(1+$U22)-1 -> -0.026262487 | AB22: =(1+H22)/(1+$U22)-1 -> -0.0072576386 | AC22: =AC21*(1+V22) -> 132.64451 | AD22: =AD21*(1+W22) -> 85.872317 | AE22: =AE21*(1+X22) -> 106.95556 | AF22: =AF21*(1+Y22) -> 105.68529 | AG22: =AG21*(1+Z22) -> 106.95279 | AH22: =AH21*(1+AA22) -> 99.981502 | AI22: =AI21*(1+AB22) -> 100.53266 | AJ22: ='Data Descriptors 2'!$V22-'Data Descriptors 2'!$X22 -> -0.1139133 | AK22: ='Data Descriptors 2'!$V22-'Data Descriptors 2'!$Y22 -> -0.12429066
A23: 1930 | B23: =('[1]S&P 500 & Raw Data'!B6-'[1]S&P 500 & Raw Data'!B5+'[1]S&P 500 & Raw Data'!C6)/'[1]S&P 500 & Raw Data'!B5 -> -0.25123636 | C23: ='[1]Small Cap'!B4 -> -0.5003 | D23: 0.0455 | E23: ='[1]S&P 500 & Raw Data'!F6 -> 0.045409314 | F23: ='[1]S&P 500 & Raw Data'!J6 -> 0.0053978095 | G23: ='[1]Home Prices'!B6/'[1]Home Prices'!B5-1 -> -0.043 | H23: ='[1]Gold Prices'!B5/'[1]Gold Prices'!B4-1 -> 0.00096946195 | I23: =I22*(1+B23) -> 98.745288 | J23: =J22*(1+C23) -> 42.662362 | K23: =K22*(1+D23) -> 111.17568 | L23: =L22*(1+E23) -> 109.84575 | M23: =M22*(1+F23) -> 106.90854 | N23: =N22*(1+G23) -> 95.129225 | O23: =O22*(1+H23) -> 100.04845 | P23: =B23-D23 -> -0.29673636 | Q23: =B23-E23 -> -0.29664568 | R23: ='Data Descriptors 2'!$C23-'Data Descriptors 2'!$B23 -> -0.24906364 | S23: =B23-F23 -> -0.25663417 | U23: ='[1]Inflation Rate'!C28 -> -0.0639535 | V23: =(1+B23)/(1+$U23)-1 -> -0.20007859 | W23: =(1+C23)/(1+$U23)-1 -> -0.466159 | X23: =(1+D23)/(1+$U23)-1 -> 0.11693169 | Y23: =(1+E23)/(1+$U23)-1 -> 0.11683481 | Z23: =(1+F23)/(1+$U23)-1 -> 0.074089599 | AA23: =(1+G23)/(1+$U23)-1 -> 0.022385106 | AB23: =(1+H23)/(1+$U23)-1 -> 0.069358693 | AC23: =AC22*(1+V23) -> 106.10518 | AD23: =AD22*(1+W23) -> 45.842164 | AE23: =AE22*(1+X23) -> 119.46206 | AF23: =AF22*(1+Y23) -> 118.03301 | AG23: =AG22*(1+Z23) -> 114.87688 | AH23: =AH22*(1+AA23) -> 102.2196 | AI23: =AI22*(1+AB23) -> 107.50547 | AJ23: ='Data Descriptors 2'!$V23-'Data Descriptors 2'!$X23 -> -0.31701028 | AK23: ='Data Descriptors 2'!$V23-'Data Descriptors 2'!$Y23 -> -0.3169134
A24: 1931 | B24: =('[1]S&P 500 & Raw Data'!B7-'[1]S&P 500 & Raw Data'!B6+'[1]S&P 500 & Raw Data'!C7)/'[1]S&P 500 & Raw Data'!B6 -> -0.43837549 | C24: ='[1]Small Cap'!B5 -> -0.4466 | D24: 0.0231 | E24: ='[1]S&P 500 & Raw Data'!F7 -> -0.02558856 | F24: ='[1]S&P 500 & Raw Data'!J7 -> -0.15680775 | G24: ='[1]Home Prices'!B7/'[1]Home Prices'!B6-1 -> -0.081504702 | H24: ='[1]Gold Prices'!B6/'[1]Gold Prices'!B5-1 -> -0.17384988 | I24: =I23*(1+B24) -> 55.457774 | J24: =J23*(1+C24) -> 23.609351 | K24: =K23*(1+D24) -> 113.74383 | L24: =L23*(1+E24) -> 107.03496 | M24: =M23*(1+F24) -> 90.144455 | N24: =N23*(1+G24) -> 87.375746 | O24: =O23*(1+H24) -> 82.655039 | P24: =B24-D24 -> -0.46147549 | Q24: =B24-E24 -> -0.41278693 | R24: ='Data Descriptors 2'!$C24-'Data Descriptors 2'!$B24 -> -0.0082245111 | S24: =B24-F24 -> -0.28156774 | U24: ='[1]Inflation Rate'!C29 -> -0.0931677 | V24: =(1+B24)/(1+$U24)-1 -> -0.38067434 | W24: =(1+C24)/(1+$U24)-1 -> -0.38974384 | X24: =(1+D24)/(1+$U24)-1 -> 0.12821301 | Y24: =(1+E24)/(1+$U24)-1 -> 0.074522203 | Z24: =(1+F24)/(1+$U24)-1 -> -0.070178412 | AA24: =(1+G24)/(1+$U24)-1 -> 0.012861251 | AB24: =(1+H24)/(1+$U24)-1 -> -0.088971444 | AC24: =AC23*(1+V24) -> 65.713662 | AD24: =AD23*(1+W24) -> 27.975463 | AE24: =AE23*(1+X24) -> 134.77865 | AF24: =AF23*(1+Y24) -> 126.82909 | AG24: =AG23*(1+Z24) -> 106.815 | AH24: =AH23*(1+AA24) -> 103.53427 | AI24: =AI23*(1+AB24) -> 97.940557 | AJ24: ='Data Descriptors 2'!$V24-'Data Descriptors 2'!$X24 -> -0.50888735 | AK24: ='Data Descriptors 2'!$V24-'Data Descriptors 2'!$Y24 -> -0.45519654
A25: 1932 | B25: =('[1]S&P 500 & Raw Data'!B8-'[1]S&P 500 & Raw Data'!B7+'[1]S&P 500 & Raw Data'!C8)/'[1]S&P 500 & Raw Data'!B7 -> -0.086423645 | C25: ='[1]Small Cap'!B6 -> 0.2049 | D25: 0.0107 | E25: ='[1]S&P 500 & Raw Data'!F8 -> 0.08790307 | F25: ='[1]S&P 500 & Raw Data'!J8 -> 0.23589602 | G25: ='[1]Home Prices'!B8/'[1]Home Prices'!B7-1 -> -0.10466439 | H25: ='[1]Gold Prices'!B7/'[1]Gold Prices'!B6-1 -> 0.21277843 | I25: =I24*(1+B25) -> 50.664911 | J25: =J24*(1+C25) -> 28.446907 | K25: =K24*(1+D25) -> 114.96089 | L25: =L24*(1+E25) -> 116.44366 | M25: =M24*(1+F25) -> 111.40917 | N25: =N24*(1+G25) -> 78.230616 | O25: =O24*(1+H25) -> 100.24225 | P25: =B25-D25 -> -0.097123645 | Q25: =B25-E25 -> -0.17432672 | R25: ='Data Descriptors 2'!$C25-'Data Descriptors 2'!$B25 -> 0.29132365 | S25: =B25-F25 -> -0.32231966 | U25: ='[1]Inflation Rate'!C30 -> -0.1027397 | V25: =(1+B25)/(1+$U25)-1 -> 0.018184305 | W25: =(1+C25)/(1+$U25)-1 -> 0.34286561 | X25: =(1+D25)/(1+$U25)-1 -> 0.12642897 | Y25: =(1+E25)/(1+$U25)-1 -> 0.21247209 | Z25: =(1+F25)/(1+$U25)-1 -> 0.37741079 | AA25: =(1+G25)/(1+$U25)-1 -> -0.0021450758 | AB25: =(1+H25)/(1+$U25)-1 -> 0.35164615 | AC25: =AC24*(1+V25) -> 66.908619 | AD25: =AD24*(1+W25) -> 37.567287 | AE25: =AE24*(1+X25) -> 151.81858 | AF25: =AF24*(1+Y25) -> 153.77673 | AG25: =AG24*(1+Z25) -> 147.12814 | AH25: =AH24*(1+AA25) -> 103.31218 | AI25: =AI24*(1+AB25) -> 132.38098 | AJ25: ='Data Descriptors 2'!$V25-'Data Descriptors 2'!$X25 -> -0.10824467 | AK25: ='Data Descriptors 2'!$V25-'Data Descriptors 2'!$Y25 -> -0.19428778
A26: 1933 | B26: =('[1]S&P 500 & Raw Data'!B9-'[1]S&P 500 & Raw Data'!B8+'[1]S&P 500 & Raw Data'!C9)/'[1]S&P 500 & Raw Data'!B8 -> 0.49982225 | C26: ='[1]Small Cap'!B7 -> 1.4834 | D26: 0.0096 | E26: ='[1]S&P 500 & Raw Data'!F9 -> 0.018552721 | F26: ='[1]S&P 500 & Raw Data'!J9 -> 0.12966894 | G26: ='[1]Home Prices'!B9/'[1]Home Prices'!B8-1 -> -0.038119441 | H26: ='[1]Gold Prices'!B8/'[1]Gold Prices'!B7-1 -> 0.27259546 | I26: =I25*(1+B26) -> 75.988361 | J26: =J25*(1+C26) -> 70.645049 | K26: =K25*(1+D26) -> 116.06452 | L26: =L25*(1+E26) -> 118.60401 | M26: =M25*(1+F26) -> 125.85548 | N26: =N25*(1+G26) -> 75.248509 | O26: =O25*(1+H26) -> 127.56783 | P26: =B26-D26 -> 0.49022225 | Q26: =B26-E26 -> 0.48126953 | R26: ='Data Descriptors 2'!$C26-'Data Descriptors 2'!$B26 -> 0.98357775 | S26: =B26-F26 -> 0.37015332 | U26: ='[1]Inflation Rate'!C31 -> 0.0076336 | V26: =(1+B26)/(1+$U26)-1 -> 0.48845995 | W26: =(1+C26)/(1+$U26)-1 -> 1.4645863 | X26: =(1+D26)/(1+$U26)-1 -> 0.001951503 | Y26: =(1+E26)/(1+$U26)-1 -> 0.0108364 | Z26: =(1+F26)/(1+$U26)-1 -> 0.12111083 | AA26: =(1+G26)/(1+$U26)-1 -> -0.045406426 | AB26: =(1+H26)/(1+$U26)-1 -> 0.26295457 | AC26: =AC25*(1+V26) -> 99.590799 | AD26: =AD25*(1+W26) -> 92.587823 | AE26: =AE25*(1+X26) -> 152.11485 | AF26: =AF25*(1+Y26) -> 155.44312 | AG26: =AG25*(1+Z26) -> 164.94695 | AH26: =AH25*(1+AA26) -> 98.621145 | AI26: =AI25*(1+AB26) -> 167.19116 | AJ26: ='Data Descriptors 2'!$V26-'Data Descriptors 2'!$X26 -> 0.48650844 | AK26: ='Data Descriptors 2'!$V26-'Data Descriptors 2'!$Y26 -> 0.47762355
A27: 1934 | B27: =('[1]S&P 500 & Raw Data'!B10-'[1]S&P 500 & Raw Data'!B9+'[1]S&P 500 & Raw Data'!C10)/'[1]S&P 500 & Raw Data'!B9 -> -0.011885657 | C27: ='[1]Small Cap'!B8 -> 0.2001 | D27: ='[1]T. Bill rates'!C12 -> 0.0027833333 | E27: ='[1]S&P 500 & Raw Data'!F10 -> 0.079634426 | F27: ='[1]S&P 500 & Raw Data'!J10 -> 0.18816429 | G27: ='[1]Home Prices'!B10/'[1]Home Prices'!B9-1 -> 0.029062087 | H27: ='[1]Gold Prices'!B9/'[1]Gold Prices'!B8-1 -> 0.31750855 | I27: =I26*(1+B27) -> 75.085189 | J27: =J26*(1+C27) -> 84.781123 | K27: =K26*(1+D27) -> 116.38756 | L27: =L26*(1+E27) -> 128.04897 | M27: =M26*(1+F27) -> 149.53699 | N27: =N26*(1+G27) -> 77.435388 | O27: =O26*(1+H27) -> 168.07171 | P27: =B27-D27 -> -0.01466899 | Q27: =B27-E27 -> -0.091520083 | R27: ='Data Descriptors 2'!$C27-'Data Descriptors 2'!$B27 -> 0.21198566 | S27: =B27-F27 -> -0.20004995 | U27: ='[1]Inflation Rate'!C32 -> 0.0151515 | V27: =(1+B27)/(1+$U27)-1 -> -0.026633618 | W27: =(1+C27)/(1+$U27)-1 -> 0.18218808 | X27: =(1+D27)/(1+$U27)-1 -> -0.012183567 | Y27: =(1+E27)/(1+$U27)-1 -> 0.063520495 | Z27: =(1+F27)/(1+$U27)-1 -> 0.17043051 | AA27: =(1+G27)/(1+$U27)-1 -> 0.013702967 | AB27: =(1+H27)/(1+$U27)-1 -> 0.29784426 | AC27: =AC26*(1+V27) -> 96.938336 | AD27: =AD26*(1+W27) -> 109.45622 | AE27: =AE26*(1+X27) -> 150.26155 | AF27: =AF26*(1+Y27) -> 165.31694 | AG27: =AG26*(1+Z27) -> 193.05894 | AH27: =AH26*(1+AA27) -> 99.972547 | AI27: =AI26*(1+AB27) -> 216.98809 | AJ27: ='Data Descriptors 2'!$V27-'Data Descriptors 2'!$X27 -> -0.01445005 | AK27: ='Data Descriptors 2'!$V27-'Data Descriptors 2'!$Y27 -> -0.090154113
A28: 1935 | B28: =('[1]S&P 500 & Raw Data'!B11-'[1]S&P 500 & Raw Data'!B10+'[1]S&P 500 & Raw Data'!C11)/'[1]S&P 500 & Raw Data'!B10 -> 0.46740421 | C28: ='[1]Small Cap'!B9 -> 0.5318 | D28: ='[1]T. Bill rates'!C13 -> 0.001675 | E28: ='[1]S&P 500 & Raw Data'!F11 -> 0.044720477 | F28: ='[1]S&P 500 & Raw Data'!J11 -> 0.13307732 | G28: ='[1]Home Prices'!B11/'[1]Home Prices'!B10-1 -> 0.097658337 | H28: ='[1]Gold Prices'!B10/'[1]Gold Prices'!B9-1 -> 0.0043240127 | I28: =I27*(1+B28) -> 110.18032 | J28: =J27*(1+C28) -> 129.86772 | K28: =K27*(1+D28) -> 116.58251 | L28: =L27*(1+E28) -> 133.77538 | M28: =M27*(1+F28) -> 169.43697 | N28: =N27*(1+G28) -> 84.997599 | O28: =O27*(1+H28) -> 168.79845 | P28: =B28-D28 -> 0.46572921 | Q28: =B28-E28 -> 0.42268373 | R28: ='Data Descriptors 2'!$C28-'Data Descriptors 2'!$B28 -> 0.064395789 | S28: =B28-F28 -> 0.33432689 | U28: ='[1]Inflation Rate'!C33 -> 0.0298507 | V28: =(1+B28)/(1+$U28)-1 -> 0.42487082 | W28: =(1+C28)/(1+$U28)-1 -> 0.48740007 | X28: =(1+D28)/(1+$U28)-1 -> -0.027359014 | Y28: =(1+E28)/(1+$U28)-1 -> 0.01443877 | Z28: =(1+F28)/(1+$U28)-1 -> 0.10023455 | AA28: =(1+G28)/(1+$U28)-1 -> 0.065842201 | AB28: =(1+H28)/(1+$U28)-1 -> -0.024786784 | AC28: =AC27*(1+V28) -> 138.12461 | AD28: =AD27*(1+W28) -> 162.80519 | AE28: =AE27*(1+X28) -> 146.15054 | AF28: =AF27*(1+Y28) -> 167.70392 | AG28: =AG27*(1+Z28) -> 212.41011 | AH28: =AH27*(1+AA28) -> 106.55496 | AI28: =AI27*(1+AB28) -> 211.60965 | AJ28: ='Data Descriptors 2'!$V28-'Data Descriptors 2'!$X28 -> 0.45222983 | AK28: ='Data Descriptors 2'!$V28-'Data Descriptors 2'!$Y28 -> 0.41043205
A29: 1936 | B29: =('[1]S&P 500 & Raw Data'!B12-'[1]S&P 500 & Raw Data'!B11+'[1]S&P 500 & Raw Data'!C12)/'[1]S&P 500 & Raw Data'!B11 -> 0.3194341 | C29: ='[1]Small Cap'!B10 -> 0.9282 | D29: ='[1]T. Bill rates'!C14 -> 0.001725 | E29: ='[1]S&P 500 & Raw Data'!F12 -> 0.050178754 | F29: ='[1]S&P 500 & Raw Data'!J12 -> 0.11383816 | G29: ='[1]Home Prices'!B12/'[1]Home Prices'!B11-1 -> 0.032186015 | H29: ='[1]Gold Prices'!B11/'[1]Gold Prices'!B10-1 -> 0.00086107922 | I29: =I28*(1+B29) -> 145.37568 | J29: =J28*(1+C29) -> 250.41095 | K29: =K28*(1+D29) -> 116.78362 | L29: =L28*(1+E29) -> 140.48806 | M29: =M28*(1+F29) -> 188.72536 | N29: =N28*(1+G29) -> 87.733333 | O29: =O28*(1+H29) -> 168.9438 | P29: =B29-D29 -> 0.3177091 | Q29: =B29-E29 -> 0.26925535 | R29: ='Data Descriptors 2'!$C29-'Data Descriptors 2'!$B29 -> 0.6087659 | S29: =B29-F29 -> 0.20559594 | U29: ='[1]Inflation Rate'!C34 -> 0.0144928 | V29: =(1+B29)/(1+$U29)-1 -> 0.30058498 | W29: =(1+C29)/(1+$U29)-1 -> 0.9006542 | X29: =(1+D29)/(1+$U29)-1 -> -0.012585402 | Y29: =(1+E29)/(1+$U29)-1 -> 0.035176153 | Z29: =(1+F29)/(1+$U29)-1 -> 0.097926135 | AA29: =(1+G29)/(1+$U29)-1 -> 0.017440454 | AB29: =(1+H29)/(1+$U29)-1 -> -0.013436981 | AC29: =AC28*(1+V29) -> 179.64279 | AD29: =AD28*(1+W29) -> 309.43637 | AE29: =AE28*(1+X29) -> 144.31118 | AF29: =AF28*(1+Y29) -> 173.60309 | AG29: =AG28*(1+Z29) -> 233.21061 | AH29: =AH28*(1+AA29) -> 108.41333 | AI29: =AI28*(1+AB29) -> 208.76625 | AJ29: ='Data Descriptors 2'!$V29-'Data Descriptors 2'!$X29 -> 0.31317039 | AK29: ='Data Descriptors 2'!$V29-'Data Descriptors 2'!$Y29 -> 0.26540883
A30: 1937 | B30: =('[1]S&P 500 & Raw Data'!B13-'[1]S&P 500 & Raw Data'!B12+'[1]S&P 500 & Raw Data'!C13)/'[1]S&P 500 & Raw Data'!B12 -> -0.35336729 | C30: ='[1]Small Cap'!B11 -> -0.5328 | D30: ='[1]T. Bill rates'!C15 -> 0.0027583333 | E30: ='[1]S&P 500 & Raw Data'!F13 -> 0.013791461 | F30: ='[1]S&P 500 & Raw Data'!J13 -> -0.044161917 | G30: ='[1]Home Prices'!B13/'[1]Home Prices'!B12-1 -> 0.025633912 | H30: ='[1]Gold Prices'!B12/'[1]Gold Prices'!B11-1 -> -0.0022942357 | I30: =I29*(1+B30) -> 94.004668 | J30: =J29*(1+C30) -> 116.99199 | K30: =K29*(1+D30) -> 117.10575 | L30: =L29*(1+E30) -> 142.4256 | M30: =M29*(1+F30) -> 180.39089 | N30: =N29*(1+G30) -> 89.982281 | O30: =O29*(1+H30) -> 168.5562 | P30: =B30-D30 -> -0.35612562 | Q30: =B30-E30 -> -0.36715875 | R30: ='Data Descriptors 2'!$C30-'Data Descriptors 2'!$B30 -> -0.17943271 | S30: =B30-F30 -> -0.30920537 | U30: ='[1]Inflation Rate'!C35 -> 0.0285714 | V30: =(1+B30)/(1+$U30)-1 -> -0.37132929 | W30: =(1+C30)/(1+$U30)-1 -> -0.54577777 | X30: =(1+D30)/(1+$U30)-1 -> -0.025096038 | Y30: =(1+E30)/(1+$U30)-1 -> -0.014369386 | Z30: =(1+F30)/(1+$U30)-1 -> -0.070712949 | AA30: =(1+G30)/(1+$U30)-1 -> -0.002855891 | AB30: =(1+H30)/(1+$U30)-1 -> -0.030008258 | AC30: =AC29*(1+V30) -> 112.93616 | AD30: =AD29*(1+W30) -> 140.55288 | AE30: =AE29*(1+X30) -> 140.68954 | AF30: =AF29*(1+Y30) -> 171.10852 | AG30: =AG29*(1+Z30) -> 216.7196 | AH30: =AH29*(1+AA30) -> 108.10371 | AI30: =AI29*(1+AB30) -> 202.50154 | AJ30: ='Data Descriptors 2'!$V30-'Data Descriptors 2'!$X30 -> -0.34623325 | AK30: ='Data Descriptors 2'!$V30-'Data Descriptors 2'!$Y30 -> -0.3569599
A31: 1938 | B31: =('[1]S&P 500 & Raw Data'!B14-'[1]S&P 500 & Raw Data'!B13+'[1]S&P 500 & Raw Data'!C14)/'[1]S&P 500 & Raw Data'!B13 -> 0.29282654 | C31: ='[1]Small Cap'!B12 -> 0.016 | D31: ='[1]T. Bill rates'!C16 -> 0.00065 | E31: ='[1]S&P 500 & Raw Data'!F14 -> 0.042132485 | F31: ='[1]S&P 500 & Raw Data'!J14 -> 0.092358817 | G31: ='[1]Home Prices'!B14/'[1]Home Prices'!B13-1 -> -0.0087368136 | H31: ='[1]Gold Prices'!B13/'[1]Gold Prices'!B12-1 -> 0.0017246335 | I31: =I30*(1+B31) -> 121.53173 | J31: =J30*(1+C31) -> 118.86387 | K31: =K30*(1+D31) -> 117.18187 | L31: =L30*(1+E31) -> 148.42634 | M31: =M30*(1+F31) -> 197.05158 | N31: =N30*(1+G31) -> 89.196123 | O31: =O30*(1+H31) -> 168.8469 | P31: =B31-D31 -> 0.29217654 | Q31: =B31-E31 -> 0.25069405 | R31: ='Data Descriptors 2'!$C31-'Data Descriptors 2'!$B31 -> -0.27682654 | S31: =B31-F31 -> 0.20046772 | U31: ='[1]Inflation Rate'!C36 -> -0.0277778 | V31: =(1+B31)/(1+$U31)-1 -> 0.32976447 | W31: =(1+C31)/(1+$U31)-1 -> 0.045028595 | X31: =(1+D31)/(1+$U31)-1 -> 0.029240024 | Y31: =(1+E31)/(1+$U31)-1 -> 0.071907724 | Z31: =(1+F31)/(1+$U31)-1 -> 0.12356909 | AA31: =(1+G31)/(1+$U31)-1 -> 0.019585015 | AB31: =(1+H31)/(1+$U31)-1 -> 0.030345361 | AC31: =AC30*(1+V31) -> 150.17849 | AD31: =AD30*(1+W31) -> 146.88178 | AE31: =AE30*(1+X31) -> 144.8033 | AF31: =AF30*(1+Y31) -> 183.41255 | AG31: =AG30*(1+Z31) -> 243.49945 | AH31: =AH30*(1+AA31) -> 110.22092 | AI31: =AI30*(1+AB31) -> 208.64652 | AJ31: ='Data Descriptors 2'!$V31-'Data Descriptors 2'!$X31 -> 0.30052445 | AK31: ='Data Descriptors 2'!$V31-'Data Descriptors 2'!$Y31 -> 0.25785675
A32: 1939 | B32: =('[1]S&P 500 & Raw Data'!B15-'[1]S&P 500 & Raw Data'!B14+'[1]S&P 500 & Raw Data'!C15)/'[1]S&P 500 & Raw Data'!B14 -> -0.010975647 | C32: ='[1]Small Cap'!B13 -> -0.0573 | D32: ='[1]T. Bill rates'!C17 -> 0.00045833333 | E32: ='[1]S&P 500 & Raw Data'!F15 -> 0.044122614 | F32: ='[1]S&P 500 & Raw Data'!J15 -> 0.079831378 | G32: ='[1]Home Prices'!B15/'[1]Home Prices'!B14-1 -> -0.013016072 | H32: ='[1]Gold Prices'!B14/'[1]Gold Prices'!B13-1 -> -0.012338594 | I32: =I31*(1+B32) -> 120.19784 | J32: =J31*(1+C32) -> 112.05297 | K32: =K31*(1+D32) -> 117.23557 | L32: =L31*(1+E32) -> 154.9753 | M32: =M31*(1+F32) -> 212.78248 | N32: =N31*(1+G32) -> 88.03514 | O32: =O31*(1+H32) -> 166.76357 | P32: =B32-D32 -> -0.01143398 | Q32: =B32-E32 -> -0.055098261 | R32: ='Data Descriptors 2'!$C32-'Data Descriptors 2'!$B32 -> -0.046324353 | S32: =B32-F32 -> -0.090807025 | U32: ='[1]Inflation Rate'!C37 -> 0 | V32: =(1+B32)/(1+$U32)-1 -> -0.010975647 | W32: =(1+C32)/(1+$U32)-1 -> -0.0573 | X32: =(1+D32)/(1+$U32)-1 -> 0.00045833333 | Y32: =(1+E32)/(1+$U32)-1 -> 0.044122614 | Z32: =(1+F32)/(1+$U32)-1 -> 0.079831378 | AA32: =(1+G32)/(1+$U32)-1 -> -0.013016072 | AB32: =(1+H32)/(1+$U32)-1 -> -0.012338594 | AC32: =AC31*(1+V32) -> 148.53019 | AD32: =AD31*(1+W32) -> 138.46545 | AE32: =AE31*(1+X32) -> 144.86967 | AF32: =AF31*(1+Y32) -> 191.50519 | AG32: =AG31*(1+Z32) -> 262.93835 | AH32: =AH31*(1+AA32) -> 108.78628 | AI32: =AI31*(1+AB32) -> 206.07212 | AJ32: ='Data Descriptors 2'!$V32-'Data Descriptors 2'!$X32 -> -0.01143398 | AK32: ='Data Descriptors 2'!$V32-'Data Descriptors 2'!$Y32 -> -0.055098261
A33: 1940 | B33: =('[1]S&P 500 & Raw Data'!B16-'[1]S&P 500 & Raw Data'!B15+'[1]S&P 500 & Raw Data'!C16)/'[1]S&P 500 & Raw Data'!B15 -> -0.10672873 | C33: ='[1]Small Cap'!B14 -> -0.3181 | D33: ='[1]T. Bill rates'!C18 -> 0.00035833333 | E33: ='[1]S&P 500 & Raw Data'!F16 -> 0.054024816 | F33: ='[1]S&P 500 & Raw Data'!J16 -> 0.086481372 | G33: ='[1]Home Prices'!B16/'[1]Home Prices'!B15-1 -> 0.033066077 | H33: ='[1]Gold Prices'!B15/'[1]Gold Prices'!B14-1 -> -0.016560139 | I33: =I32*(1+B33) -> 107.36928 | J33: =J32*(1+C33) -> 76.408918 | K33: =K32*(1+D33) -> 117.27758 | L33: =L32*(1+E33) -> 163.34781 | M33: =M32*(1+F33) -> 231.1842 | N33: =N32*(1+G33) -> 90.946116 | O33: =O32*(1+H33) -> 164.00194 | P33: =B33-D33 -> -0.10708707 | Q33: =B33-E33 -> -0.16075355 | R33: ='Data Descriptors 2'!$C33-'Data Descriptors 2'!$B33 -> -0.21137127 | S33: =B33-F33 -> -0.1932101 | U33: ='[1]Inflation Rate'!C38 -> 0.0071429 | V33: =(1+B33)/(1+$U33)-1 -> -0.11306403 | W33: =(1+C33)/(1+$U33)-1 -> -0.3229362 | X33: =(1+D33)/(1+$U33)-1 -> -0.0067364489 | Y33: =(1+E33)/(1+$U33)-1 -> 0.046549418 | Z33: =(1+F33)/(1+$U33)-1 -> 0.078775784 | AA33: =(1+G33)/(1+$U33)-1 -> 0.025739323 | AB33: =(1+H33)/(1+$U33)-1 -> -0.023534932 | AC33: =AC32*(1+V33) -> 131.73677 | AD33: =AD32*(1+W33) -> 93.749944 | AE33: =AE32*(1+X33) -> 143.89377 | AF33: =AF32*(1+Y33) -> 200.41965 | AG33: =AG32*(1+Z33) -> 283.65152 | AH33: =AH32*(1+AA33) -> 111.58636 | AI33: =AI32*(1+AB33) -> 201.22223 | AJ33: ='Data Descriptors 2'!$V33-'Data Descriptors 2'!$X33 -> -0.10632758 | AK33: ='Data Descriptors 2'!$V33-'Data Descriptors 2'!$Y33 -> -0.15961345
A34: 1941 | B34: =('[1]S&P 500 & Raw Data'!B17-'[1]S&P 500 & Raw Data'!B16+'[1]S&P 500 & Raw Data'!C17)/'[1]S&P 500 & Raw Data'!B16 -> -0.12771456 | C34: ='[1]Small Cap'!B15 -> -0.0554 | D34: ='[1]T. Bill rates'!C19 -> 0.0012916667 | E34: ='[1]S&P 500 & Raw Data'!F17 -> -0.020221976 | F34: ='[1]S&P 500 & Raw Data'!J17 -> 0.050071729 | G34: ='[1]Home Prices'!B17/'[1]Home Prices'!B16-1 -> -0.083846277 | H34: ='[1]Gold Prices'!B16/'[1]Gold Prices'!B15-1 -> 0 | I34: =I33*(1+B34) -> 93.656657 | J34: =J33*(1+C34) -> 72.175864 | K34: =K33*(1+D34) -> 117.42907 | L34: =L33*(1+E34) -> 160.0446 | M34: =M33*(1+F34) -> 242.75999 | N34: =N33*(1+G34) -> 83.320623 | O34: =O33*(1+H34) -> 164.00194 | P34: =B34-D34 -> -0.12900622 | Q34: =B34-E34 -> -0.10749258 | R34: ='Data Descriptors 2'!$C34-'Data Descriptors 2'!$B34 -> 0.072314556 | S34: =B34-F34 -> -0.17778628 | U34: ='[1]Inflation Rate'!C39 -> 0.0992908 | V34: =(1+B34)/(1+$U34)-1 -> -0.20650164 | W34: =(1+C34)/(1+$U34)-1 -> -0.14071873 | X34: =(1+D34)/(1+$U34)-1 -> -0.089147597 | Y34: =(1+E34)/(1+$U34)-1 -> -0.10871807 | Z34: =(1+F34)/(1+$U34)-1 -> -0.044773477 | AA34: =(1+G34)/(1+$U34)-1 -> -0.16659566 | AB34: =(1+H34)/(1+$U34)-1 -> -0.090322597 | AC34: =AC33*(1+V34) -> 104.53291 | AD34: =AD33*(1+W34) -> 80.557572 | AE34: =AE33*(1+X34) -> 131.06598 | AF34: =AF33*(1+Y34) -> 178.63041 | AG34: =AG33*(1+Z34) -> 270.95146 | AH34: =AH33*(1+AA34) -> 92.99656 | AI34: =AI33*(1+AB34) -> 183.04731 | AJ34: ='Data Descriptors 2'!$V34-'Data Descriptors 2'!$X34 -> -0.11735405 | AK34: ='Data Descriptors 2'!$V34-'Data Descriptors 2'!$Y34 -> -0.097783571
A35: 1942 | B35: =('[1]S&P 500 & Raw Data'!B18-'[1]S&P 500 & Raw Data'!B17+'[1]S&P 500 & Raw Data'!C18)/'[1]S&P 500 & Raw Data'!B17 -> 0.19173763 | C35: ='[1]Small Cap'!B16 -> 0.6179 | D35: ='[1]T. Bill rates'!C20 -> 0.003425 | E35: ='[1]S&P 500 & Raw Data'!F18 -> 0.022948682 | F35: ='[1]S&P 500 & Raw Data'!J18 -> 0.05179901 | G35: ='[1]Home Prices'!B18/'[1]Home Prices'!B17-1 -> 0.033330412 | H35: ='[1]Gold Prices'!B17/'[1]Gold Prices'!B16-1 -> 0 | I35: =I34*(1+B35) -> 111.61416 | J35: =J34*(1+C35) -> 116.77333 | K35: =K34*(1+D35) -> 117.83126 | L35: =L34*(1+E35) -> 163.71741 | M35: =M34*(1+F35) -> 255.33472 | N35: =N34*(1+G35) -> 86.097734 | O35: =O34*(1+H35) -> 164.00194 | P35: =B35-D35 -> 0.18831263 | Q35: =B35-E35 -> 0.16878895 | R35: ='Data Descriptors 2'!$C35-'Data Descriptors 2'!$B35 -> 0.42616237 | S35: =B35-F35 -> 0.13993862 | U35: ='[1]Inflation Rate'!C40 -> 0.0903226 | V35: =(1+B35)/(1+$U35)-1 -> 0.093013783 | W35: =(1+C35)/(1+$U35)-1 -> 0.48387275 | X35: =(1+D35)/(1+$U35)-1 -> -0.079698981 | Y35: =(1+E35)/(1+$U35)-1 -> -0.061792645 | Z35: =(1+F35)/(1+$U35)-1 -> -0.035332286 | AA35: =(1+G35)/(1+$U35)-1 -> -0.052270941 | AB35: =(1+H35)/(1+$U35)-1 -> -0.082840253 | AC35: =AC34*(1+V35) -> 114.25591 | AD35: =AD34*(1+W35) -> 119.53719 | AE35: =AE34*(1+X35) -> 120.62016 | AF35: =AF34*(1+Y35) -> 167.59236 | AG35: =AG34*(1+Z35) -> 261.37812 | AH35: =AH34*(1+AA35) -> 88.135543 | AI35: =AI34*(1+AB35) -> 167.88363 | AJ35: ='Data Descriptors 2'!$V35-'Data Descriptors 2'!$X35 -> 0.17271276 | AK35: ='Data Descriptors 2'!$V35-'Data Descriptors 2'!$Y35 -> 0.15480643
A36: 1943 | B36: =('[1]S&P 500 & Raw Data'!B19-'[1]S&P 500 & Raw Data'!B18+'[1]S&P 500 & Raw Data'!C19)/'[1]S&P 500 & Raw Data'!B18 -> 0.2506131 | C36: ='[1]Small Cap'!B17 -> 1.3797 | D36: ='[1]T. Bill rates'!C21 -> 0.0038 | E36: ='[1]S&P 500 & Raw Data'!F19 -> 0.0249 | F36: ='[1]S&P 500 & Raw Data'!J19 -> 0.080446701 | G36: ='[1]Home Prices'!B19/'[1]Home Prices'!B18-1 -> 0.1144626 | H36: ='[1]Gold Prices'!B18/'[1]Gold Prices'!B17-1 -> 0 | I36: =I35*(1+B36) -> 139.58613 | J36: =J35*(1+C36) -> 277.88549 | K36: =K35*(1+D36) -> 118.27902 | L36: =L35*(1+E36) -> 167.79397 | M36: =M35*(1+F36) -> 275.87555 | N36: =N35*(1+G36) -> 95.952704 | O36: =O35*(1+H36) -> 164.00194 | P36: =B36-D36 -> 0.2468131 | Q36: =B36-E36 -> 0.2257131 | R36: ='Data Descriptors 2'!$C36-'Data Descriptors 2'!$B36 -> 1.1290869 | S36: =B36-F36 -> 0.1701664 | U36: ='[1]Inflation Rate'!C41 -> 0.0295858 | V36: =(1+B36)/(1+$U36)-1 -> 0.21467594 | W36: =(1+C36)/(1+$U36)-1 -> 1.3113178 | X36: =(1+D36)/(1+$U36)-1 -> -0.025044829 | Y36: =(1+E36)/(1+$U36)-1 -> -0.0045511506 | Z36: =(1+F36)/(1+$U36)-1 -> 0.04939938 | AA36: =(1+G36)/(1+$U36)-1 -> 0.082437811 | AB36: =(1+H36)/(1+$U36)-1 -> -0.028735633 | AC36: =AC35*(1+V36) -> 138.7839 | AD36: =AD35*(1+W36) -> 276.28843 | AE36: =AE35*(1+X36) -> 117.59925 | AF36: =AF35*(1+Y36) -> 166.82962 | AG36: =AG35*(1+Z36) -> 274.29004 | AH36: =AH35*(1+AA36) -> 95.401244 | AI36: =AI35*(1+AB36) -> 163.05938 | AJ36: ='Data Descriptors 2'!$V36-'Data Descriptors 2'!$X36 -> 0.23972077 | AK36: ='Data Descriptors 2'!$V36-'Data Descriptors 2'!$Y36 -> 0.21922709
A37: 1944 | B37: =('[1]S&P 500 & Raw Data'!B20-'[1]S&P 500 & Raw Data'!B19+'[1]S&P 500 & Raw Data'!C20)/'[1]S&P 500 & Raw Data'!B19 -> 0.19030677 | C37: ='[1]Small Cap'!B18 -> 0.6973 | D37: ='[1]T. Bill rates'!C22 -> 0.0038 | E37: ='[1]S&P 500 & Raw Data'!F20 -> 0.025776112 | F37: ='[1]S&P 500 & Raw Data'!J20 -> 0.065658636 | G37: ='[1]Home Prices'!B20/'[1]Home Prices'!B19-1 -> 0.16584227 | H37: ='[1]Gold Prices'!B19/'[1]Gold Prices'!B18-1 -> 0 | I37: =I36*(1+B37) -> 166.15032 | J37: =J36*(1+C37) -> 471.65505 | K37: =K36*(1+D37) -> 118.72848 | L37: =L36*(1+E37) -> 172.11905 | M37: =M36*(1+F37) -> 293.98917 | N37: =N36*(1+G37) -> 111.86572 | O37: =O36*(1+H37) -> 164.00194 | P37: =B37-D37 -> 0.18650677 | Q37: =B37-E37 -> 0.16453066 | R37: ='Data Descriptors 2'!$C37-'Data Descriptors 2'!$B37 -> 0.50699323 | S37: =B37-F37 -> 0.12464813 | U37: ='[1]Inflation Rate'!C42 -> 0.0229885 | V37: =(1+B37)/(1+$U37)-1 -> 0.16355831 | W37: =(1+C37)/(1+$U37)-1 -> 0.65915844 | X37: =(1+D37)/(1+$U37)-1 -> -0.018757298 | Y37: =(1+E37)/(1+$U37)-1 -> 0.0027249686 | Z37: =(1+F37)/(1+$U37)-1 -> 0.041711257 | AA37: =(1+G37)/(1+$U37)-1 -> 0.13964358 | AB37: =(1+H37)/(1+$U37)-1 -> -0.022471905 | AC37: =AC36*(1+V37) -> 161.48316 | AD37: =AD36*(1+W37) -> 458.40627 | AE37: =AE36*(1+X37) -> 115.3934 | AF37: =AF36*(1+Y37) -> 167.28423 | AG37: =AG36*(1+Z37) -> 285.73102 | AH37: =AH36*(1+AA37) -> 108.72341 | AI37: =AI36*(1+AB37) -> 159.39513 | AJ37: ='Data Descriptors 2'!$V37-'Data Descriptors 2'!$X37 -> 0.18231561 | AK37: ='Data Descriptors 2'!$V37-'Data Descriptors 2'!$Y37 -> 0.16083334
A38: 1945 | B38: =('[1]S&P 500 & Raw Data'!B21-'[1]S&P 500 & Raw Data'!B20+'[1]S&P 500 & Raw Data'!C21)/'[1]S&P 500 & Raw Data'!B20 -> 0.35821084 | C38: ='[1]Small Cap'!B19 -> 0.9109 | D38: ='[1]T. Bill rates'!C23 -> 0.0038 | E38: ='[1]S&P 500 & Raw Data'!F21 -> 0.038044173 | F38: ='[1]S&P 500 & Raw Data'!J21 -> 0.067998655 | G38: ='[1]Home Prices'!B21/'[1]Home Prices'!B20-1 -> 0.11777376 | H38: ='[1]Gold Prices'!B20/'[1]Gold Prices'!B19-1 -> 0.025406204 | I38: =I37*(1+B38) -> 225.66717 | J38: =J37*(1+C38) -> 901.28563 | K38: =K37*(1+D38) -> 119.17965 | L38: =L37*(1+E38) -> 178.66717 | M38: =M37*(1+F38) -> 313.98003 | N38: =N37*(1+G38) -> 125.04057 | O38: =O37*(1+H38) -> 168.1686 | P38: =B38-D38 -> 0.35441084 | Q38: =B38-E38 -> 0.32016667 | R38: ='Data Descriptors 2'!$C38-'Data Descriptors 2'!$B38 -> 0.55268916 | S38: =B38-F38 -> 0.29021219 | U38: ='[1]Inflation Rate'!C43 -> 0.0224719 | V38: =(1+B38)/(1+$U38)-1 -> 0.32836007 | W38: =(1+C38)/(1+$U38)-1 -> 0.86890222 | X38: =(1+D38)/(1+$U38)-1 -> -0.018261529 | Y38: =(1+E38)/(1+$U38)-1 -> 0.015230026 | Z38: =(1+F38)/(1+$U38)-1 -> 0.044526167 | AA38: =(1+G38)/(1+$U38)-1 -> 0.093207319 | AB38: =(1+H38)/(1+$U38)-1 -> 0.0028698137 | AC38: =AC37*(1+V38) -> 214.50779 | AD38: =AD37*(1+W38) -> 856.7165 | AE38: =AE37*(1+X38) -> 113.28614 | AF38: =AF37*(1+Y38) -> 169.83197 | AG38: =AG37*(1+Z38) -> 298.45353 | AH38: =AH37*(1+AA38) -> 118.85723 | AI38: =AI37*(1+AB38) -> 159.85256 | AJ38: ='Data Descriptors 2'!$V38-'Data Descriptors 2'!$X38 -> 0.3466216 | AK38: ='Data Descriptors 2'!$V38-'Data Descriptors 2'!$Y38 -> 0.31313004
... A52: 1959 | B52: =('[1]S&P 500 & Raw Data'!B35-'[1]S&P 500 & Raw Data'!B34+'[1]S&P 500 & Raw Data'!C35)/'[1]S&P 500 & Raw Data'!B34 -> 0.12056457 | C52: ='[1]Small Cap'!B33 -> 0.1274 | D52: ='[1]T. Bill rates'!C37 -> 0.033860159 | E52: ='[1]S&P 500 & Raw Data'!F35 -> -0.026466313 | F52: ='[1]S&P 500 & Raw Data'!J35 -> 0.015743431 | G52: ='[1]Home Prices'!B35/'[1]Home Prices'!B34-1 -> 0.0010952903 | H52: ='[1]Gold Prices'!B34/'[1]Gold Prices'!B33-1 -> 0 | I52: =I51*(1+B52) -> 1608.9516 | J52: =J51*(1+C52) -> 4822.1565 | K52: =K51*(1+D52) -> 149.84231 | L52: =L51*(1+E52) -> 214.55509 | M52: =M51*(1+F52) -> 440.94935 | N52: =N51*(1+G52) -> 259.31167 | O52: =O51*(1+H52) -> 170.05814 | P52: =B52-D52 -> 0.086704412 | Q52: =B52-E52 -> 0.14703088 | R52: ='Data Descriptors 2'!$C52-'Data Descriptors 2'!$B52 -> 0.0068354284 | S52: =B52-F52 -> 0.10482114 | U52: ='[1]Inflation Rate'!C57 -> 0.017301 | V52: =(1+B52)/(1+$U52)-1 -> 0.10150739 | W52: =(1+C52)/(1+$U52)-1 -> 0.10822657 | X52: =(1+D52)/(1+$U52)-1 -> 0.016277542 | Y52: =(1+E52)/(1+$U52)-1 -> -0.043022972 | Z52: =(1+F52)/(1+$U52)-1 -> -0.0015310799 | AA52: =(1+G52)/(1+$U52)-1 -> -0.015930103 | AB52: =(1+H52)/(1+$U52)-1 -> -0.017006766 | AC52: =AC51*(1+V52) -> 946.76414 | AD52: =AD51*(1+W52) -> 2837.5277 | AE52: =AE51*(1+X52) -> 88.172525 | AF52: =AF51*(1+Y52) -> 126.25182 | AG52: =AG51*(1+Z52) -> 259.47022 | AH52: =AH51*(1+AA52) -> 152.58817 | AI52: =AI51*(1+AB52) -> 100.06823 | AJ52: ='Data Descriptors 2'!$V52-'Data Descriptors 2'!$X52 -> 0.085229851 | AK52: ='Data Descriptors 2'!$V52-'Data Descriptors 2'!$Y52 -> 0.14453036
A53: 1960 | B53: =('[1]S&P 500 & Raw Data'!B36-'[1]S&P 500 & Raw Data'!B35+'[1]S&P 500 & Raw Data'!C36)/'[1]S&P 500 & Raw Data'!B35 -> 0.0033653531 | C53: ='[1]Small Cap'!B34 -> -0.0349 | D53: ='[1]T. Bill rates'!C38 -> 0.028729719 | E53: ='[1]S&P 500 & Raw Data'!F36 -> 0.11639504 | F53: ='[1]S&P 500 & Raw Data'!J36 -> 0.066631872 | G53: ='[1]Home Prices'!B36/'[1]Home Prices'!B35-1 -> 0.0076586433 | H53: ='[1]Gold Prices'!B35/'[1]Gold Prices'!B34-1 -> 0.0048433048 | I53: =I52*(1+B53) -> 1614.3663 | J53: =J52*(1+C53) -> 4653.8633 | K53: =K52*(1+D53) -> 154.14724 | L53: =L52*(1+E53) -> 239.52824 | M53: =M52*(1+F53) -> 470.33063 | N53: =N52*(1+G53) -> 261.29765 | O53: =O52*(1+H53) -> 170.88178 | P53: =B53-D53 -> -0.025364366 | Q53: =B53-E53 -> -0.11302968 | R53: ='Data Descriptors 2'!$C53-'Data Descriptors 2'!$B53 -> -0.038265353 | S53: =B53-F53 -> -0.063266518 | T53: =((I53/100)^(1/(A53-$A$21+1)))-((L53/100)^(1/(A53-$A$21+1))) -> 0.061119788 | U53: ='[1]Inflation Rate'!C58 -> 0.0136054 | V53: =(1+B53)/(1+$U53)-1 -> -0.010102597 | W53: =(1+C53)/(1+$U53)-1 -> -0.047854323 | X53: =(1+D53)/(1+$U53)-1 -> 0.014921309 | Y53: =(1+E53)/(1+$U53)-1 -> 0.10140991 | Z53: =(1+F53)/(1+$U53)-1 -> 0.052314709 | AA53: =(1+G53)/(1+$U53)-1 -> -0.0058669347 | AB53: =(1+H53)/(1+$U53)-1 -> -0.0086444835 | AC53: =AC52*(1+V53) -> 937.19936 | AD53: =AD52*(1+W53) -> 2701.7398 | AE53: =AE52*(1+X53) -> 89.488175 | AF53: =AF52*(1+Y53) -> 139.055 | AG53: =AG52*(1+Z53) -> 273.04433 | AH53: =AH52*(1+AA53) -> 151.69295 | AI53: =AI52*(1+AB53) -> 99.203195 | AJ53: ='Data Descriptors 2'!$V53-'Data Descriptors 2'!$X53 -> -0.025023905 | AK53: ='Data Descriptors 2'!$V53-'Data Descriptors 2'!$Y53 -> -0.11151251
A54: 1961 | B54: =('[1]S&P 500 & Raw Data'!B37-'[1]S&P 500 & Raw Data'!B36+'[1]S&P 500 & Raw Data'!C37)/'[1]S&P 500 & Raw Data'!B36 -> 0.26637713 | C54: ='[1]Small Cap'!B35 -> 0.2983 | D54: ='[1]T. Bill rates'!C39 -> 0.0235249 | E54: ='[1]S&P 500 & Raw Data'!F37 -> 0.020609208 | F54: ='[1]S&P 500 & Raw Data'!J37 -> 0.051 | G54: ='[1]Home Prices'!B37/'[1]Home Prices'!B36-1 -> 0.009771987 | H54: ='[1]Gold Prices'!B36/'[1]Gold Prices'!B35-1 -> -0.00056705415 | I54: =I53*(1+B54) -> 2044.3966 | J54: =J53*(1+C54) -> 6042.1107 | K54: =K53*(1+D54) -> 157.77354 | L54: =L53*(1+E54) -> 244.46473 | M54: =M53*(1+F54) -> 494.31749 | N54: =N53*(1+G54) -> 263.85104 | O54: =O53*(1+H54) -> 170.78488 | P54: =B54-D54 -> 0.24285223 | Q54: =B54-E54 -> 0.24576792 | R54: ='Data Descriptors 2'!$C54-'Data Descriptors 2'!$B54 -> 0.03192287 | S54: =B54-F54 -> 0.21537713 | T54: =((I54/100)^(1/(A54-$A$21+1)))-((L54/100)^(1/(A54-$A$21+1))) -> 0.066173592 | U54: ='[1]Inflation Rate'!C59 -> 0.0067114 | V54: =(1+B54)/(1+$U54)-1 -> 0.25793463 | W54: =(1+C54)/(1+$U54)-1 -> 0.28964468 | X54: =(1+D54)/(1+$U54)-1 -> 0.01670141 | Y54: =(1+E54)/(1+$U54)-1 -> 0.013805156 | Z54: =(1+F54)/(1+$U54)-1 -> 0.043993343 | AA54: =(1+G54)/(1+$U54)-1 -> 0.0030401831 | AB54: =(1+H54)/(1+$U54)-1 -> -0.0072299312 | AC54: =AC53*(1+V54) -> 1178.9355 | AD54: =AD53*(1+W54) -> 3484.2843 | AE54: =AE53*(1+X54) -> 90.982753 | AF54: =AF53*(1+Y54) -> 140.97468 | AG54: =AG53*(1+Z54) -> 285.05646 | AH54: =AH53*(1+AA54) -> 152.15412 | AI54: =AI53*(1+AB54) -> 98.485963 | AJ54: ='Data Descriptors 2'!$V54-'Data Descriptors 2'!$X54 -> 0.24123322 | AK54: ='Data Descriptors 2'!$V54-'Data Descriptors 2'!$Y54 -> 0.24412947
A55: 1962 | B55: =('[1]S&P 500 & Raw Data'!B38-'[1]S&P 500 & Raw Data'!B37+'[1]S&P 500 & Raw Data'!C38)/'[1]S&P 500 & Raw Data'!B37 -> -0.088114605 | C55: ='[1]Small Cap'!B36 -> -0.0976 | D55: ='[1]T. Bill rates'!C40 -> 0.027723695 | E55: ='[1]S&P 500 & Raw Data'!F38 -> 0.056935441 | F55: ='[1]S&P 500 & Raw Data'!J38 -> 0.06495328 | G55: ='[1]Home Prices'!B38/'[1]Home Prices'!B37-1 -> 0.0032258065 | H55: ='[1]Gold Prices'!B37/'[1]Gold Prices'!B36-1 -> -0.00056737589 | I55: =I54*(1+B55) -> 1864.2554 | J55: =J54*(1+C55) -> 5452.4007 | K55: =K54*(1+D55) -> 162.1476 | L55: =L54*(1+E55) -> 258.38343 | M55: =M54*(1+F55) -> 526.42504 | N55: =N54*(1+G55) -> 264.70218 | O55: =O54*(1+H55) -> 170.68798 | P55: =B55-D55 -> -0.1158383 | Q55: =B55-E55 -> -0.14505005 | R55: ='Data Descriptors 2'!$C55-'Data Descriptors 2'!$B55 -> -0.0094853948 | S55: =B55-F55 -> -0.15306789 | T55: =((I55/100)^(1/(A55-$A$21+1)))-((L55/100)^(1/(A55-$A$21+1))) -> 0.059683465 | U55: ='[1]Inflation Rate'!C60 -> 0.0133333 | V55: =(1+B55)/(1+$U55)-1 -> -0.10011307 | W55: =(1+C55)/(1+$U55)-1 -> -0.10947365 | X55: =(1+D55)/(1+$U55)-1 -> 0.014201048 | Y55: =(1+E55)/(1+$U55)-1 -> 0.04302843 | Z55: =(1+F55)/(1+$U55)-1 -> 0.050940771 | AA55: =(1+G55)/(1+$U55)-1 -> -0.0099745005 | AB55: =(1+H55)/(1+$U55)-1 -> -0.013717773 | AC55: =AC54*(1+V55) -> 1060.9087 | AD55: =AD54*(1+W55) -> 3102.847 | AE55: =AE54*(1+X55) -> 92.274804 | AF55: =AF54*(1+Y55) -> 147.0406 | AG55: =AG54*(1+Z55) -> 299.57746 | AH55: =AH54*(1+AA55) -> 150.63646 | AI55: =AI54*(1+AB55) -> 97.134955 | AJ55: ='Data Descriptors 2'!$V55-'Data Descriptors 2'!$X55 -> -0.11431412 | AK55: ='Data Descriptors 2'!$V55-'Data Descriptors 2'!$Y55 -> -0.1431415
A56: 1963 | B56: =('[1]S&P 500 & Raw Data'!B39-'[1]S&P 500 & Raw Data'!B38+'[1]S&P 500 & Raw Data'!C39)/'[1]S&P 500 & Raw Data'!B38 -> 0.22611927 | C56: ='[1]Small Cap'!B37 -> 0.1993 | D56: ='[1]T. Bill rates'!C41 -> 0.031560241 | E56: ='[1]S&P 500 & Raw Data'!F39 -> 0.016841621 | F56: ='[1]S&P 500 & Raw Data'!J39 -> 0.054644806 | G56: ='[1]Home Prices'!B39/'[1]Home Prices'!B38-1 -> 0.021436227 | H56: ='[1]Gold Prices'!B38/'[1]Gold Prices'!B37-1 -> -0.0039738859 | I56: =I55*(1+B56) -> 2285.7995 | J56: =J55*(1+C56) -> 6539.0641 | K56: =K55*(1+D56) -> 167.26502 | L56: =L55*(1+E56) -> 262.73503 | M56: =M55*(1+F56) -> 555.19143 | N56: =N55*(1+G56) -> 270.37639 | O56: =O55*(1+H56) -> 170.00969 | P56: =B56-D56 -> 0.19455903 | Q56: =B56-E56 -> 0.20927765 | R56: ='Data Descriptors 2'!$C56-'Data Descriptors 2'!$B56 -> -0.026819271 | S56: =B56-F56 -> 0.17147447 | T56: =((I56/100)^(1/(A56-$A$21+1)))-((L56/100)^(1/(A56-$A$21+1))) -> 0.063618994 | U56: ='[1]Inflation Rate'!C61 -> 0.0164474 | V56: =(1+B56)/(1+$U56)-1 -> 0.20627912 | W56: =(1+C56)/(1+$U56)-1 -> 0.17989381 | X56: =(1+D56)/(1+$U56)-1 -> 0.014868296 | Y56: =(1+E56)/(1+$U56)-1 -> 0.00038784175 | Z56: =(1+F56)/(1+$U56)-1 -> 0.037579324 | AA56: =(1+G56)/(1+$U56)-1 -> 0.0049081017 | AB56: =(1+H56)/(1+$U56)-1 -> -0.020090844 | AC56: =AC55*(1+V56) -> 1279.752 | AD56: =AD55*(1+W56) -> 3661.0299 | AE56: =AE55*(1+X56) -> 93.646773 | AF56: =AF55*(1+Y56) -> 147.09763 | AG56: =AG55*(1+Z56) -> 310.83537 | AH56: =AH55*(1+AA56) -> 151.3758 | AI56: =AI55*(1+AB56) -> 95.183432 | AJ56: ='Data Descriptors 2'!$V56-'Data Descriptors 2'!$X56 -> 0.19141082 | AK56: ='Data Descriptors 2'!$V56-'Data Descriptors 2'!$Y56 -> 0.20589127
A57: 1964 | B57: =('[1]S&P 500 & Raw Data'!B40-'[1]S&P 500 & Raw Data'!B39+'[1]S&P 500 & Raw Data'!C40)/'[1]S&P 500 & Raw Data'!B39 -> 0.16415456 | C57: ='[1]Small Cap'!B38 -> 0.2315 | D57: ='[1]T. Bill rates'!C42 -> 0.035457371 | E57: ='[1]S&P 500 & Raw Data'!F40 -> 0.037280649 | F57: ='[1]S&P 500 & Raw Data'!J40 -> 0.051617393 | G57: ='[1]Home Prices'!B40/'[1]Home Prices'!B39-1 -> 0.012591815 | H57: ='[1]Gold Prices'!B39/'[1]Gold Prices'!B38-1 -> 0.00028498148 | I57: =I56*(1+B57) -> 2661.0239 | J57: =J56*(1+C57) -> 8052.8575 | K57: =K56*(1+D57) -> 173.1958 | L57: =L56*(1+E57) -> 272.52996 | M57: =M56*(1+F57) -> 583.84896 | N57: =N56*(1+G57) -> 273.78092 | O57: =O56*(1+H57) -> 170.05814 | P57: =B57-D57 -> 0.12869719 | Q57: =B57-E57 -> 0.12687391 | R57: ='Data Descriptors 2'!$C57-'Data Descriptors 2'!$B57 -> 0.067345441 | S57: =B57-F57 -> 0.11253717 | T57: =((I57/100)^(1/(A57-$A$21+1)))-((L57/100)^(1/(A57-$A$21+1))) -> 0.065267777 | U57: ='[1]Inflation Rate'!C62 -> 0.0097087 | V57: =(1+B57)/(1+$U57)-1 -> 0.15296081 | W57: =(1+C57)/(1+$U57)-1 -> 0.2196587 | X57: =(1+D57)/(1+$U57)-1 -> 0.025501088 | Y57: =(1+E57)/(1+$U57)-1 -> 0.027306835 | Z57: =(1+F57)/(1+$U57)-1 -> 0.041505726 | AA57: =(1+G57)/(1+$U57)-1 -> 0.0028553932 | AB57: =(1+H57)/(1+$U57)-1 -> -0.0093331062 | AC57: =AC56*(1+V57) -> 1475.5039 | AD57: =AD56*(1+W57) -> 4465.207 | AE57: =AE56*(1+X57) -> 96.034867 | AF57: =AF56*(1+Y57) -> 151.1144 | AG57: =AG56*(1+Z57) -> 323.73682 | AH57: =AH56*(1+AA57) -> 151.80804 | AI57: =AI56*(1+AB57) -> 94.295075 | AJ57: ='Data Descriptors 2'!$V57-'Data Descriptors 2'!$X57 -> 0.12745972 | AK57: ='Data Descriptors 2'!$V57-'Data Descriptors 2'!$Y57 -> 0.12565397
A58: 1965 | B58: =('[1]S&P 500 & Raw Data'!B41-'[1]S&P 500 & Raw Data'!B40+'[1]S&P 500 & Raw Data'!C41)/'[1]S&P 500 & Raw Data'!B40 -> 0.12399242 | C58: ='[1]Small Cap'!B39 -> 0.4566 | D58: ='[1]T. Bill rates'!C43 -> 0.039490763 | E58: ='[1]S&P 500 & Raw Data'!F41 -> 0.0071885509 | F58: ='[1]S&P 500 & Raw Data'!J41 -> 0.031900095 | G58: ='[1]Home Prices'!B41/'[1]Home Prices'!B40-1 -> 0.016580311 | H58: ='[1]Gold Prices'!B40/'[1]Gold Prices'!B39-1 -> 0.00056980057 | I58: =I57*(1+B58) -> 2990.9707 | J58: =J57*(1+C58) -> 11729.792 | K58: =K57*(1+D58) -> 180.03543 | L58: =L57*(1+E58) -> 274.48906 | M58: =M57*(1+F58) -> 602.4738 | N58: =N57*(1+G58) -> 278.3203 | O58: =O57*(1+H58) -> 170.15504 | P58: =B58-D58 -> 0.084501662 | Q58: =B58-E58 -> 0.11680387 | R58: ='Data Descriptors 2'!$C58-'Data Descriptors 2'!$B58 -> 0.33260758 | S58: =B58-F58 -> 0.09209233 | T58: =((I58/100)^(1/(A58-$A$21+1)))-((L58/100)^(1/(A58-$A$21+1))) -> 0.066617942 | U58: ='[1]Inflation Rate'!C63 -> 0.0192308 | V58: =(1+B58)/(1+$U58)-1 -> 0.10278499 | W58: =(1+C58)/(1+$U58)-1 -> 0.42911694 | X58: =(1+D58)/(1+$U58)-1 -> 0.019877699 | Y58: =(1+E58)/(1+$U58)-1 -> -0.011815036 | Z58: =(1+F58)/(1+$U58)-1 -> 0.012430251 | AA58: =(1+G58)/(1+$U58)-1 -> -0.0026004798 | AB58: =(1+H58)/(1+$U58)-1 -> -0.018308905 | AC58: =AC57*(1+V58) -> 1627.1635 | AD58: =AD57*(1+W58) -> 6381.303 | AE58: =AE57*(1+X58) -> 97.94382 | AF58: =AF57*(1+Y58) -> 149.32897 | AG58: =AG57*(1+Z58) -> 327.76095 | AH58: =AH57*(1+AA58) -> 151.41326 | AI58: =AI57*(1+AB58) -> 92.568635 | AJ58: ='Data Descriptors 2'!$V58-'Data Descriptors 2'!$X58 -> 0.082907288 | AK58: ='Data Descriptors 2'!$V58-'Data Descriptors 2'!$Y58 -> 0.11460002
A59: 1966 | B59: =('[1]S&P 500 & Raw Data'!B42-'[1]S&P 500 & Raw Data'!B41+'[1]S&P 500 & Raw Data'!C42)/'[1]S&P 500 & Raw Data'!B41 -> -0.099709542 | C59: ='[1]Small Cap'!B40 -> -0.0949 | D59: ='[1]T. Bill rates'!C44 -> 0.0485572 | E59: ='[1]S&P 500 & Raw Data'!F42 -> 0.029079409 | F59: ='[1]S&P 500 & Raw Data'!J42 -> -0.034453616 | G59: ='[1]Home Prices'!B42/'[1]Home Prices'!B41-1 -> 0.012232416 | H59: ='[1]Gold Prices'!B41/'[1]Gold Prices'!B40-1 -> 0.00028473804 | I59: =I58*(1+B59) -> 2692.7424 | J59: =J58*(1+C59) -> 10616.635 | K59: =K58*(1+D59) -> 188.77745 | L59: =L58*(1+E59) -> 282.47104 | M59: =M58*(1+F59) -> 581.7164 | N59: =N58*(1+G59) -> 281.72482 | O59: =O58*(1+H59) -> 170.20349 | P59: =B59-D59 -> -0.14826674 | Q59: =B59-E59 -> -0.12878895 | R59: ='Data Descriptors 2'!$C59-'Data Descriptors 2'!$B59 -> 0.0048095424 | S59: =B59-F59 -> -0.065255926 | T59: =((I59/100)^(1/(A59-$A$21+1)))-((L59/100)^(1/(A59-$A$21+1))) -> 0.06112372 | U59: ='[1]Inflation Rate'!C64 -> 0.0345912 | V59: =(1+B59)/(1+$U59)-1 -> -0.12981044 | W59: =(1+C59)/(1+$U59)-1 -> -0.12516171 | X59: =(1+D59)/(1+$U59)-1 -> 0.013499052 | Y59: =(1+E59)/(1+$U59)-1 -> -0.0053275059 | Z59: =(1+F59)/(1+$U59)-1 -> -0.066736326 | AA59: =(1+G59)/(1+$U59)-1 -> -0.021611226 | AB59: =(1+H59)/(1+$U59)-1 -> -0.033159437 | AC59: =AC58*(1+V59) -> 1415.9407 | AD59: =AD58*(1+W59) -> 5582.6082 | AE59: =AE58*(1+X59) -> 99.265968 | AF59: =AF58*(1+Y59) -> 148.53342 | AG59: =AG58*(1+Z59) -> 305.88739 | AH59: =AH58*(1+AA59) -> 148.14104 | AI59: =AI58*(1+AB59) -> 89.499111 | AJ59: ='Data Descriptors 2'!$V59-'Data Descriptors 2'!$X59 -> -0.14330949 | AK59: ='Data Descriptors 2'!$V59-'Data Descriptors 2'!$Y59 -> -0.12448294
A60: 1967 | B60: =('[1]S&P 500 & Raw Data'!B43-'[1]S&P 500 & Raw Data'!B42+'[1]S&P 500 & Raw Data'!C43)/'[1]S&P 500 & Raw Data'!B42 -> 0.23802967 | C60: ='[1]Small Cap'!B41 -> 1.1679 | D60: ='[1]T. Bill rates'!C45 -> 0.042934538 | E60: ='[1]S&P 500 & Raw Data'!F43 -> -0.01580621 | F60: ='[1]S&P 500 & Raw Data'!J43 -> 0.0089522661 | G60: ='[1]Home Prices'!B43/'[1]Home Prices'!B42-1 -> 0.023162135 | H60: ='[1]Gold Prices'!B42/'[1]Gold Prices'!B41-1 -> -0.0051238258 | I60: =I59*(1+B60) -> 3333.6949 | J60: =J59*(1+C60) -> 23015.803 | K60: =K59*(1+D60) -> 196.88252 | L60: =L59*(1+E60) -> 278.00624 | M60: =M59*(1+F60) -> 586.92408 | N60: =N59*(1+G60) -> 288.25017 | O60: =O59*(1+H60) -> 169.3314 | P60: =B60-D60 -> 0.19509513 | Q60: =B60-E60 -> 0.25383588 | R60: ='Data Descriptors 2'!$C60-'Data Descriptors 2'!$B60 -> 0.92987033 | S60: =B60-F60 -> 0.2290774 | T60: =((I60/100)^(1/(A60-$A$21+1)))-((L60/100)^(1/(A60-$A$21+1))) -> 0.065732839 | U60: ='[1]Inflation Rate'!C65 -> 0.0303951 | V60: =(1+B60)/(1+$U60)-1 -> 0.20150966 | W60: =(1+C60)/(1+$U60)-1 -> 1.1039502 | X60: =(1+D60)/(1+$U60)-1 -> 0.012169544 | Y60: =(1+E60)/(1+$U60)-1 -> -0.044838441 | Z60: =(1+F60)/(1+$U60)-1 -> -0.020810303 | AA60: =(1+G60)/(1+$U60)-1 -> -0.0070196035 | AB60: =(1+H60)/(1+$U60)-1 -> -0.034471171 | AC60: =AC59*(1+V60) -> 1701.2664 | AD60: =AD59*(1+W60) -> 11745.53 | AE60: =AE59*(1+X60) -> 100.47399 | AF60: =AF59*(1+Y60) -> 141.87342 | AG60: =AG59*(1+Z60) -> 299.52178 | AH60: =AH59*(1+AA60) -> 147.10115 | AI60: =AI59*(1+AB60) -> 86.413972 | AJ60: ='Data Descriptors 2'!$V60-'Data Descriptors 2'!$X60 -> 0.18934012 | AK60: ='Data Descriptors 2'!$V60-'Data Descriptors 2'!$Y60 -> 0.2463481
A61: 1968 | B61: =('[1]S&P 500 & Raw Data'!B44-'[1]S&P 500 & Raw Data'!B43+'[1]S&P 500 & Raw Data'!C44)/'[1]S&P 500 & Raw Data'!B43 -> 0.10814863 | C61: ='[1]Small Cap'!B42 -> 0.607 | D61: ='[1]T. Bill rates'!C46 -> 0.053376 | E61: ='[1]S&P 500 & Raw Data'!F44 -> 0.032746197 | F61: ='[1]S&P 500 & Raw Data'!J44 -> 0.048451462 | G61: ='[1]Home Prices'!B44/'[1]Home Prices'!B43-1 -> 0.041338583 | H61: ='[1]Gold Prices'!B43/'[1]Gold Prices'!B42-1 -> 0.12474964 | I61: =I60*(1+B61) -> 3694.2294 | J61: =J60*(1+C61) -> 36986.395 | K61: =K60*(1+D61) -> 207.39133 | L61: =L60*(1+E61) -> 287.10989 | M61: =M60*(1+F61) -> 615.36141 | N61: =N60*(1+G61) -> 300.16603 | O61: =O60*(1+H61) -> 190.45543 | P61: =B61-D61 -> 0.054772627 | Q61: =B61-E61 -> 0.07540243 | R61: ='Data Descriptors 2'!$C61-'Data Descriptors 2'!$B61 -> 0.49885137 | S61: =B61-F61 -> 0.059697164 | T61: =((I61/100)^(1/(A61-$A$21+1)))-((L61/100)^(1/(A61-$A$21+1))) -> 0.065966278 | U61: ='[1]Inflation Rate'!C66 -> 0.0471976 | V61: =(1+B61)/(1+$U61)-1 -> 0.05820394 | W61: =(1+C61)/(1+$U61)-1 -> 0.53457189 | X61: =(1+D61)/(1+$U61)-1 -> 0.0058999371 | Y61: =(1+E61)/(1+$U61)-1 -> -0.013800073 | Z61: =(1+F61)/(1+$U61)-1 -> 0.0011973502 | AA61: =(1+G61)/(1+$U61)-1 -> -0.0055949492 | AB61: =(1+H61)/(1+$U61)-1 -> 0.074056742 | AC61: =AC60*(1+V61) -> 1800.2868 | AD61: =AD60*(1+W61) -> 18024.36 | AE61: =AE60*(1+X61) -> 101.06678 | AF61: =AF60*(1+Y61) -> 139.91555 | AG61: =AG60*(1+Z61) -> 299.88041 | AH61: =AH60*(1+AA61) -> 146.27812 | AI61: =AI60*(1+AB61) -> 92.813509 | AJ61: ='Data Descriptors 2'!$V61-'Data Descriptors 2'!$X61 -> 0.052304003 | AK61: ='Data Descriptors 2'!$V61-'Data Descriptors 2'!$Y61 -> 0.072004013
A62: 1969 | B62: =('[1]S&P 500 & Raw Data'!B45-'[1]S&P 500 & Raw Data'!B44+'[1]S&P 500 & Raw Data'!C45)/'[1]S&P 500 & Raw Data'!B44 -> -0.082413711 | C62: ='[1]Small Cap'!B43 -> -0.3305 | D62: ='[1]T. Bill rates'!C47 -> 0.066684677 | E62: ='[1]S&P 500 & Raw Data'!F45 -> -0.050140493 | F62: ='[1]S&P 500 & Raw Data'!J45 -> -0.020251643 | G62: ='[1]Home Prices'!B45/'[1]Home Prices'!B44-1 -> 0.069943289 | H62: ='[1]Gold Prices'!B44/'[1]Gold Prices'!B43-1 -> 0.050114475 | I62: =I61*(1+B62) -> 3389.7743 | J62: =J61*(1+C62) -> 24762.392 | K62: =K61*(1+D62) -> 221.22115 | L62: =L61*(1+E62) -> 272.71406 | M62: =M61*(1+F62) -> 602.89933 | N62: =N61*(1+G62) -> 321.16063 | O62: =O61*(1+H62) -> 200 | P62: =B62-D62 -> -0.14909839 | Q62: =B62-E62 -> -0.032273218 | R62: ='Data Descriptors 2'!$C62-'Data Descriptors 2'!$B62 -> -0.24808629 | S62: =B62-F62 -> -0.062162068 | T62: =((I62/100)^(1/(A62-$A$21+1)))-((L62/100)^(1/(A62-$A$21+1))) -> 0.063333873 | U62: ='[1]Inflation Rate'!C67 -> 0.0619718 | V62: =(1+B62)/(1+$U62)-1 -> -0.13595984 | W62: =(1+C62)/(1+$U62)-1 -> -0.36956895 | X62: =(1+D62)/(1+$U62)-1 -> 0.0044378555 | Y62: =(1+E62)/(1+$U62)-1 -> -0.10556993 | Z62: =(1+F62)/(1+$U62)-1 -> -0.07742526 | AA62: =(1+G62)/(1+$U62)-1 -> 0.0075063097 | AB62: =(1+H62)/(1+$U62)-1 -> -0.011165386 | AC62: =AC61*(1+V62) -> 1555.5201 | AD62: =AD61*(1+W62) -> 11363.116 | AE62: =AE61*(1+X62) -> 101.5153 | AF62: =AF61*(1+Y62) -> 125.14468 | AG62: =AG61*(1+Z62) -> 276.66209 | AH62: =AH61*(1+AA62) -> 147.37613 | AI62: =AI61*(1+AB62) -> 91.777211 | AJ62: ='Data Descriptors 2'!$V62-'Data Descriptors 2'!$X62 -> -0.14039769 | AK62: ='Data Descriptors 2'!$V62-'Data Descriptors 2'!$Y62 -> -0.030389901
A63: 1970 | B63: =('[1]S&P 500 & Raw Data'!B46-'[1]S&P 500 & Raw Data'!B45+'[1]S&P 500 & Raw Data'!C46)/'[1]S&P 500 & Raw Data'!B45 -> 0.035611449 | C63: ='[1]Small Cap'!B44 -> -0.19 | D63: ='[1]T. Bill rates'!C48 -> 0.06391 | E63: ='[1]S&P 500 & Raw Data'!F46 -> 0.16754737 | F63: ='[1]S&P 500 & Raw Data'!J46 -> 0.056495677 | G63: ='[1]Home Prices'!B46/'[1]Home Prices'!B45-1 -> 0.082155477 | H63: ='[1]Gold Prices'!B45/'[1]Gold Prices'!B44-1 -> -0.094476744 | I63: =I62*(1+B63) -> 3510.4891 | J63: =J62*(1+C63) -> 20057.537 | K63: =K62*(1+D63) -> 235.35939 | L63: =L62*(1+E63) -> 318.40658 | M63: =M62*(1+F63) -> 636.96054 | N63: =N62*(1+G63) -> 347.54573 | O63: =O62*(1+H63) -> 181.10465 | P63: =B63-D63 -> -0.028298551 | Q63: =B63-E63 -> -0.13193592 | R63: ='Data Descriptors 2'!$C63-'Data Descriptors 2'!$B63 -> -0.22561145 | S63: =B63-F63 -> -0.020884228 | T63: =((I63/100)^(1/(A63-$A$21+1)))-((L63/100)^(1/(A63-$A$21+1))) -> 0.058972567 | U63: ='[1]Inflation Rate'!C68 -> 0.0557029 | V63: =(1+B63)/(1+$U63)-1 -> -0.01903135 | W63: =(1+C63)/(1+$U63)-1 -> -0.23273868 | X63: =(1+D63)/(1+$U63)-1 -> 0.0077740622 | Y63: =(1+E63)/(1+$U63)-1 -> 0.10594313 | Z63: =(1+F63)/(1+$U63)-1 -> 0.00075094666 | AA63: =(1+G63)/(1+$U63)-1 -> 0.025056838 | AB63: =(1+H63)/(1+$U63)-1 -> -0.1422556 | AC63: =AC62*(1+V63) -> 1525.9165 | AD63: =AD62*(1+W63) -> 8718.4795 | AE63: =AE62*(1+X63) -> 102.30449 | AF63: =AF62*(1+Y63) -> 138.4029 | AG63: =AG62*(1+Z63) -> 276.86985 | AH63: =AH62*(1+AA63) -> 151.06891 | AI63: =AI62*(1+AB63) -> 78.721389 | AJ63: ='Data Descriptors 2'!$V63-'Data Descriptors 2'!$X63 -> -0.026805412 | AK63: ='Data Descriptors 2'!$V63-'Data Descriptors 2'!$Y63 -> -0.12497448
A64: 1971 | B64: =('[1]S&P 500 & Raw Data'!B47-'[1]S&P 500 & Raw Data'!B46+'[1]S&P 500 & Raw Data'!C47)/'[1]S&P 500 & Raw Data'!B46 -> 0.1422115 | C64: ='[1]Small Cap'!B45 -> 0.1649 | D64: ='[1]T. Bill rates'!C49 -> 0.04334257 | E64: ='[1]S&P 500 & Raw Data'!F47 -> 0.097868966 | F64: ='[1]S&P 500 & Raw Data'!J47 -> 0.14001466 | G64: ='[1]Home Prices'!B47/'[1]Home Prices'!B46-1 -> 0.04244898 | H64: ='[1]Gold Prices'!B46/'[1]Gold Prices'!B45-1 -> 0.16693419 | I64: =I63*(1+B64) -> 4009.721 | J64: =J63*(1+C64) -> 23365.025 | K64: =K63*(1+D64) -> 245.56047 | L64: =L63*(1+E64) -> 349.5687 | M64: =M63*(1+F64) -> 726.14435 | N64: =N63*(1+G64) -> 362.29869 | O64: =O63*(1+H64) -> 211.33721 | P64: =B64-D64 -> 0.098868933 | Q64: =B64-E64 -> 0.044342537 | R64: ='Data Descriptors 2'!$C64-'Data Descriptors 2'!$B64 -> 0.022688497 | S64: =B64-F64 -> 0.0021968412 | T64: =((I64/100)^(1/(A64-$A$21+1)))-((L64/100)^(1/(A64-$A$21+1))) -> 0.058660637 | U64: ='[1]Inflation Rate'!C69 -> 0.0326633 | V64: =(1+B64)/(1+$U64)-1 -> 0.10608318 | W64: =(1+C64)/(1+$U64)-1 -> 0.12805403 | X64: =(1+D64)/(1+$U64)-1 -> 0.010341483 | Y64: =(1+E64)/(1+$U64)-1 -> 0.063143201 | Z64: =(1+F64)/(1+$U64)-1 -> 0.10395582 | AA64: =(1+G64)/(1+$U64)-1 -> 0.009476157 | AB64: =(1+H64)/(1+$U64)-1 -> 0.13002388 | AC64: =AC63*(1+V64) -> 1687.7906 | AD64: =AD63*(1+W64) -> 9834.9159 | AE64: =AE63*(1+X64) -> 103.36247 | AF64: =AF63*(1+Y64) -> 147.1421 | AG64: =AG63*(1+Z64) -> 305.65209 | AH64: =AH63*(1+AA64) -> 152.50046 | AI64: =AI63*(1+AB64) -> 88.957049 | AJ64: ='Data Descriptors 2'!$V64-'Data Descriptors 2'!$X64 -> 0.095741693 | AK64: ='Data Descriptors 2'!$V64-'Data Descriptors 2'!$Y64 -> 0.042939975
... A117: 2024 | B117: =('[1]S&P 500 & Raw Data'!B100-'[1]S&P 500 & Raw Data'!B99+'[1]S&P 500 & Raw Data'!C100)/'[1]S&P 500 & Raw Data'!B99 -> 0.24878611 | C117: ='[1]Small Cap'!B98 -> 0.0862 | D117: ='[1]T. Bill rates'!C102 -> 0.0497 | E117: ='[1]S&P 500 & Raw Data'!F100 -> -0.016371801 | F117: ='[1]S&P 500 & Raw Data'!J100 -> 0.017363556 | G117: ='[1]Home Prices'!B100/'[1]Home Prices'!B99-1 -> 0.042441001 | H117: ='[1]Gold Prices'!B99/'[1]Gold Prices'!B98-1 -> 0.25957034 | I117: =I116*(1+B117) -> 982817.82 | J117: =J116*(1+C117) -> 4586545.6 | K117: =K116*(1+D117) -> 2360.8169 | L117: =L116*(1+E117) -> 7159.4493 | M117: =M116*(1+F117) -> 50385.148 | N117: =N116*(1+G117) -> 5553.6977 | O117: =O116*(1+H117) -> 12649.467 | P117: =B117-D117 -> 0.19908611 | Q117: =B117-E117 -> 0.26515791 | R117: ='Data Descriptors 2'!$C117-'Data Descriptors 2'!$B117 -> -0.16258611 | S117: =B117-F117 -> 0.23142256 | T117: =((I117/100)^(1/(A117-$A$21+1)))-((L117/100)^(1/(A117-$A$21+1))) -> 0.054394707 | U117: ='[1]Inflation Rate'!C122 -> 0.0275 | V117: =(1+B117)/(1+$U117)-1 -> 0.21536361 | W117: =(1+C117)/(1+$U117)-1 -> 0.057128954 | X117: =(1+D117)/(1+$U117)-1 -> 0.021605839 | Y117: =(1+E117)/(1+$U117)-1 -> -0.042697617 | Z117: =(1+F117)/(1+$U117)-1 -> -0.0098651523 | AA117: =(1+G117)/(1+$U117)-1 -> 0.01454112 | AB117: =(1+H117)/(1+$U117)-1 -> 0.22585921 | AC117: =AC116*(1+V117) -> 53945.922 | AD117: =AD116*(1+W117) -> 251751.06 | AE117: =AE116*(1+X117) -> 129.58296 | AF117: =AF116*(1+Y117) -> 392.97527 | AG117: =AG116*(1+Z117) -> 2765.5922 | AH117: =AH116*(1+AA117) -> 304.83711 | AI117: =AI116*(1+AB117) -> 694.31705 | AJ117: ='Data Descriptors 2'!$V117-'Data Descriptors 2'!$X117 -> 0.19375777 | AK117: ='Data Descriptors 2'!$V117-'Data Descriptors 2'!$Y117 -> 0.25806123
A119: Arithmetic Average Historical Return | L119: Equity Risk Premium (Arithmetic) | N119: Standard Error | Q119: Small Cap Premium (Arithmetic) | U119: Arithmetic Average Annual Real Return
A120: 1928-2024 | B120: =AVERAGE(B21:B117) -> 0.11794146 | C120: =AVERAGE(C21:C117) -> 0.17523918 | D120: =AVERAGE(D21:D117) -> 0.033552896 | E120: =AVERAGE(E21:E117) -> 0.047917109 | F120: =AVERAGE(F21:F117) -> 0.068998801 | G120: =AVERAGE(G21:G117) -> 0.044095847 | H120: =AVERAGE(H21:H117) -> 0.067542065 | L120: Stocks - T.Bills | M120: Stocks - T.Bonds | N120: Stocks - T.Bills | O120: Stocks - T.Bonds | Q120: S&P 500 minus Lowest Decile | R120: Standard Error | V120: S&P 500 (includes dividends)2 | W120: ='Data Descriptors 2'!$W$20 -> US Small cap (bottom decile)22 | X120: 3-month T. Bill (Real) | Y120: !0-year T.Bonds | Z120: Baa Corp Bonds | AA120: Real Estate3 | AB120: Gold | AH120: Standard Error
A121: 1975-2024 | B121: =AVERAGE(B68:B117) -> 0.13554135 | C121: =AVERAGE(C68:C117) -> 0.157762 | D121: =AVERAGE(D68:D117) -> 0.043014595 | E121: =AVERAGE(E68:E117) -> 0.065209173 | F121: =AVERAGE(F68:F117) -> 0.089381592 | G121: =AVERAGE(G68:G117) -> 0.054301207 | H121: =AVERAGE(H68:H117) -> 0.075588268 | L121: =B120-D120 -> 0.084388563 | M121: =B120-E120 -> 0.070024349 | N121: =STDEV(P21:P117)/(($A$117-$A$21+1)^0.5) -> 0.020106756 | O121: =STDEV(Q21:Q117)/(($A$117-$A$21+1)^0.5) -> 0.021243404 | Q121: =C120-B120 -> 0.057297717 | R121: =STDEV(R21:R117)/(($A$117-$A$21+1)^0.5) -> 0.027722646 | U121: 1928-2024 | V121: =AVERAGE(V21:V117) -> 0.085485479 | W121: =AVERAGE(W21:W117) -> 0.14112707 | X121: =AVERAGE(X21:X117) -> 0.0033924409 | Y121: =AVERAGE(Y21:Y117) -> 0.018030417 | Z121: =AVERAGE(Z21:Z117) -> 0.038531071 | AA121: =AVERAGE(AA21:AA117) -> 0.012791099 | AB121: =AVERAGE(AB21:AB117) -> 0.034768197 | AH121: Stocks - T.Bills | AI121: Stocks - T.Bonds
A122: 2015-2024 | B122: =AVERAGE(B108:B117) -> 0.14113611 | C122: =AVERAGE(C108:C117) -> 0.0666 | D122: =AVERAGE(D108:D117) -> 0.017765959 | E122: =AVERAGE(E108:E117) -> 0.0057260163 | F122: =AVERAGE(F108:F117) -> 0.038098453 | G122: =AVERAGE(G108:G117) -> 0.069775616 | H122: =AVERAGE(H108:H117) -> 0.086991611 | L122: =B121-D121 -> 0.092526752 | M122: =B121-E121 -> 0.070332173 | N122: =STDEV(P68:P117)/(($A$117-$A$68+1)^0.5) -> 0.023018787 | O122: =STDEV(Q68:Q117)/(($A$117-$A$68+1)^0.5) -> 0.02673559 | Q122: =C121-B121 -> 0.022220653 | R122: =STDEV(R68:R117)/(($A$117-$A$68+1)^0.5) -> 0.027815774 | U122: 1975-2024 | V122: =AVERAGE(V68:V117) -> 0.095396183 | W122: =AVERAGE(W68:W117) -> 0.11609606 | X122: =AVERAGE(X68:X117) -> 0.0058596568 | Y122: =AVERAGE(Y68:Y117) -> 0.028370274 | Z122: =AVERAGE(Z68:Z117) -> 0.051587488 | AA122: =AVERAGE(AA68:AA117) -> 0.016765254 | AB122: =AVERAGE(AB68:AB117) -> 0.036006691 | AH122: =STDEV(AJ22:AJ118)/(($A$116-$A$21+1)^0.5) -> 0.019718723 | AI122: =STDEV(AK22:AK118)/(($A$116-$A$21+1)^0.5) -> 0.020777239
L123: =B122-D122 -> 0.12337015 | M123: =B122-E122 -> 0.13541009 | N123: =STDEV(P108:P117)/(($A$117-$A$108+1)^0.5) -> 0.050392894 | O123: =STDEV(Q108:Q117)/(($A$117-$A$108+1)^0.5) -> 0.040102345 | Q123: =C122-B122 -> -0.074536109 | R123: =STDEV(R108:R117)/(($A$117-$A$108+1)^0.5) -> 0.03628532 | U123: 2015-2024 | V123: =AVERAGE(V108:V117) -> 0.1084603 | W123: =AVERAGE(W108:W117) -> 0.036317705 | X123: =AVERAGE(X108:X117) -> -0.011601519 | Y123: =AVERAGE(Y108:Y117) -> -0.022264254 | Z123: =AVERAGE(Z108:Z117) -> 0.0089585262 | AA123: =AVERAGE(AA108:AA117) -> 0.038483228 | AB123: =AVERAGE(AB108:AB117) -> 0.056177077 | AH123: =STDEV(AJ68:AJ118)/(($A$116-$A$67+1)^0.5) -> 0.022299903 | AI123: =STDEV(AK68:AK118)/(($A$116-$A$67+1)^0.5) -> 0.025924895
A124: Geometric Average Historical Return | L124: Equity Risk Premium (Geometric) | Q124: Small Cap Premium (Geometric) | U124: Geometric Average Historical Return | AH124: =STDEV(AJ108:AJ118)/(($A$116-$A$107+1)^0.5) -> 0.048268537 | AI124: =STDEV(AK108:AK118)/(($A$116-$A$107+1)^0.5) -> 0.038358209
A125: 1928-2024 | B125: =(I117/100)^(1/($A$117-$A$21+1))-1 -> 0.099409577 | C125: =(J117/100)^(1/($A$117-$A$21+1))-1 -> 0.11700869 | D125: =(K117/100)^(1/($A$117-$A$21+1))-1 -> 0.033130734 | E125: =(L117/100)^(1/($A$117-$A$21+1))-1 -> 0.04501487 | F125: =(M117/100)^(1/($A$117-$A$21+1))-1 -> 0.066249374 | G125: =(N117/100)^(1/($A$117-$A$21+1))-1 -> 0.042282351 | H125: =(O117/100)^(1/($A$117-$A$21+1))-1 -> 0.051164893 | L125: Stocks - T.Bills | M125: Stocks - T.Bonds | Q125: S&P 500 minus Lowest Decile | U125: 1928-2024 | V125: =(AC117/100)^(1/($A$117-$A$21+1))-1 -> 0.067000252 | W125: =(AD117/100)^(1/($A$117-$A$21+1))-1 -> 0.084080568 | X125: =(AE117/100)^(1/($A$117-$A$21+1))-1 -> 0.0026752333 | Y125: =(AF117/100)^(1/($A$117-$A$21+1))-1 -> 0.014209038 | Z125: =(AG117/100)^(1/($A$117-$A$21+1))-1 -> 0.034817573 | AA125: =(AH117/100)^(1/($A$117-$A$21+1))-1 -> 0.011557071 | AB125: =(AI117/100)^(1/($A$117-$A$21+1))-1 -> 0.020177765
A126: 1975-2024 | B126: =(I117/I67)^(1/($A$117-$A$67))-1 -> 0.1226365 | C126: =(J117/J67)^(1/($A$117-$A$67))-1 -> 0.1292437 | D126: =(K117/K67)^(1/($A$117-$A$67))-1 -> 0.042474958 | E126: =(L117/L67)^(1/($A$117-$A$67))-1 -> 0.060479738 | F126: =(M117/M67)^(1/($A$117-$A$67))-1 -> 0.086198205 | G126: =(N117/N67)^(1/($A$117-$A$67))-1 -> 0.052760766 | H126: =(O117/O67)^(1/($A$117-$A$67))-1 -> 0.054197694 | L126: =B125-D125 -> 0.066278842 | M126: =B125-E125 -> 0.054394707 | Q126: =C125-B125 -> 0.017599118 | U126: 1975-2024 | V126: =(AC117/AC67)^(1/($A$116-$A$66))-1 -> 0.082857458 | W126: =(AD117/AD67)^(1/($A$116-$A$66))-1 -> 0.089230547 | X126: =(AE117/AE67)^(1/($A$116-$A$66))-1 -> 0.0055363293 | Y126: =(AF117/AF67)^(1/($A$116-$A$66))-1 -> 0.022903135 | Z126: =(AG117/AG67)^(1/($A$116-$A$66))-1 -> 0.047710305 | AA126: =(AH117/AH67)^(1/($A$116-$A$66))-1 -> 0.015457674 | AB126: =(AI117/AI67)^(1/($A$116-$A$66))-1 -> 0.016843686
A127: 2015-2024 | B127: =(I117/I107)^(1/($A$117-$A$107))-1 -> 0.12977048 | C127: =(J117/J107)^(1/($A$117-$A$107))-1 -> 0.052108368 | D127: =(K117/K107)^(1/($A$117-$A$107))-1 -> 0.017610103 | E127: =(L117/L107)^(1/($A$117-$A$107))-1 -> 0.0026517006 | F127: =(M117/M107)^(1/($A$117-$A$107))-1 -> 0.034351546 | G127: =(N117/N107)^(1/($A$117-$A$107))-1 -> 0.068943022 | H127: =(O117/O107)^(1/($A$117-$A$107))-1 -> 0.080297725 | L127: =B126-D126 -> 0.080161539 | M127: =B126-E126 -> 0.062156759 | Q127: =C126-B126 -> 0.0066072066 | U127: 2015-2024 | V127: =(AC117/AC107)^(1/($A$116-$A$106))-1 -> 0.096998866 | W127: =(AD117/AD107)^(1/($A$116-$A$106))-1 -> 0.021589527 | X127: =(AE117/AE107)^(1/($A$116-$A$106))-1 -> -0.011908036 | Y127: =(AF117/AF107)^(1/($A$116-$A$106))-1 -> -0.026432535 | Z127: =(AG117/AG107)^(1/($A$116-$A$106))-1 -> 0.0043477823 | AA127: =(AH117/AH107)^(1/($A$116-$A$106))-1 -> 0.037935853 | AB127: =(AI117/AI107)^(1/($A$116-$A$106))-1 -> 0.048961186
L128: =B127-D127 -> 0.11216037 | M128: =B127-E127 -> 0.12711878 | Q128: =C127-B127 -> -0.077662109
A129: Note
A130: * Prior to 1971, gold prices were fixed and with the gold standard in place, and were mostly stable.

Sheet Graphs and Charts
A9: 95% confidence interval of annual returns.
A41: VaR 95% of Returns

Sheet Statistical Tests
A8: Stock | B8: Shares Owned | C8: Initial Price | D8: Current Price | E8: Initial Position | F8: Current Position | G8: $ Returns | H8: % Returns | I8: Years Owned | J8: Annualized | K8: Log Price △
A9: AAPL | B9: 2 | C9: =(137.46 + 142.16) / 2 -> 139.81 | D9: {=_xlfn.STOCKHISTORY("AAPL", DATE(2025,10,24), DATE(2025,10,24),0,0,1)} -> 262.82 | E9: =B9*C9 -> 279.62 | F9: =B9*D9 -> 525.64 | G9: =F9-E9 -> 246.02 | H9: =(F9-E9)/E9 -> 0.87983692 | I9: 3 | J9: =((1 + H9) ^ (1/I9)) - 1 -> 0.23416547 | K9: =LN(F9) - LN(E9) -> 0.63118503
A10: COST | B10: 2 | C10: 450 | D10: {=_xlfn.STOCKHISTORY("COST", DATE(2025,10,24), DATE(2025,10,24),0,0,1)} -> 932.14 | E10: =B10*C10 -> 900 | F10: =B10*D10 -> 1864.28 | G10: =F10-E10 -> 964.28 | H10: =(F10-E10)/E10 -> 1.0714222 | I10: 2 | J10: =((1 + H10) ^ (1/I10)) - 1 -> 0.43924363 | K10: =LN(F10) - LN(E10) -> 0.72823544
A11: DIA | B11: 1 | C11: 293 | D11: {=_xlfn.STOCKHISTORY("ARCX:DIA", DATE(2025,10,24), DATE(2025,10,24),0,0,1)} -> 472.21 | E11: =B11*C11 -> 293 | F11: =B11*D11 -> 472.21 | G11: =F11-E11 -> 179.21 | H11: =(F11-E11)/E11 -> 0.61163823 | I11: 3 | J11: =((1 + H11) ^ (1/I11)) - 1 -> 0.17243611 | K11: =LN(F11) - LN(E11) -> 0.47725119
A12: DJT | B12: 1 | C12: 19.5 | D12: 15.84 | E12: =B12*C12 -> 19.5 | F12: =B12*D12 -> 15.84 | G12: =F12-E12 -> -3.66 | H12: =(F12-E12)/E12 -> -0.18769231 | I12: 1 | J12: =((1 + H12) ^ (1/I12)) - 1 -> -0.18769231 | K12: =LN(F12) - LN(E12) -> -0.20787608
A13: GEHC | B13: 2 | C13: 59.97 | D13: {=_xlfn.STOCKHISTORY("GEHC", DATE(2025,10,24), DATE(2025,10,24),0,0,1)} -> 78.14 | E13: =B13*C13 -> 119.94 | F13: =B13*D13 -> 156.28 | G13: =F13-E13 -> 36.34 | H13: =(F13-E13)/E13 -> 0.30298483 | I13: 2 | J13: =((1 + H13) ^ (1/I13)) - 1 -> 0.14148361 | K13: =LN(F13) - LN(E13) -> 0.26465765
A14: ONEQ | B14: 2 | C14: 43.74 | D14: {=_xlfn.STOCKHISTORY("ONEQ", DATE(2025,10,24), DATE(2025,10,24),0,0,1)} -> 91.2631 | E14: =B14*C14 -> 87.48 | F14: =B14*D14 -> 182.5262 | G14: =F14-E14 -> 95.0462 | H14: =(F14-E14)/E14 -> 1.0864906 | I14: 3 | J14: =((1 + H14) ^ (1/I14)) - 1 -> 0.27782725 | K14: =LN(F14) - LN(E14) -> 0.73548353
A15: RDNT | B15: 1 | C15: 54.84 | D15: {=_xlfn.STOCKHISTORY("RDNT", DATE(2025,10,24), DATE(2025,10,24),0,0,1)} -> 83.41 | E15: =B15*C15 -> 54.84 | F15: =B15*D15 -> 83.41 | G15: =F15-E15 -> 28.57 | H15: =(F15-E15)/E15 -> 0.52097009 | I15: 1 | J15: =((1 + H15) ^ (1/I15)) - 1 -> 0.52097009 | K15: =LN(F15) - LN(E15) -> 0.41934835
D17: Total | E17: =SUM(E9:E15) -> 1754.38 | F17: =SUM(F9:F15) -> 3300.1862
D19: Total Portfolio Returns | E19: =(F17 - E17) / E17 -> 0.88111253
D20: Annualized Total Porftoflio Returns (3 yrs) | E20: =((1 + E19) ^ (1 / 3)) - 1 -> 0.23444457
C23: Annual Returns | D23: Percentage | E23: $ Amount | H23: (Nominal) Monthly Returns | I23: Excess Monthly Returns
C24: Average | D24: =AVERAGE(J9:J15) -> 0.22834769 | E24: =$F$17 * D24 -> 753.58991 | G24: Average | H24: ='Data Descriptors 1'!B10 -> 0.02479555 | I24: {='Data Descriptors 1'!G10:H10} -> 0.020989629 | J24: 0.020989629
C25: STDEV | D25: =_xlfn.STDEV.P(J9:J15) -> 0.21258538 | E25: =$F$17 * D25 -> 701.57133 | G25: Standard Deviation | H25: ='Data Descriptors 1'!B14 -> 0.051061058 | I25: {='Data Descriptors 1'!G14:H14} -> 0.051785706 | J25: 0.051785706
C26: VaR (5%) | D26: =_xlfn.NORM.INV(0.05,0.228,0.213) -> -0.12235382 | E26: =$F$17 * D26 -> -403.7904
F30: Annual | G30: Monthly
E31: Market Rate (S&P 500 from (1928 - 2024) | F31: 0.118 | G31: =((1 + F31) ^ (1/12)) - 1 -> 0.0093384483
E32: Risk Free Rate (3-mo T-bills 1928 - 2024) | F32: 0.034 | G32: =((1 + F32) ^ (1/12)) - 1 -> 0.0027901165
E33: Risk Premium | F33: =F31 - F32 -> 0.084 | G33: =G31 - G32 -> 0.0065483318
E35: Beta (S&P 500 as Index) | F35: =_xlfn.COVARIANCE.S('Data Descriptors 1'!R3:R38, 'Data Descriptors 1'!AU10:AU45) / _xlfn.VAR.S('Data Descriptors 1'!AU10:AU45) -> 0.32921947
E36: Beta (Dow Jones as Index) | F36: =_xlfn.COVARIANCE.S('Data Descriptors 1'!R3:R38, 'Data Descriptors 1'!BH10:BH45) / _xlfn.VAR.S('Data Descriptors 1'!BH10:BH45) -> 0.48569026
E37: Expected Monthly Return of Portfolio Re (𝜷 S&P) | F37: =G32 + F35 * G33 -> 0.0049459548
E38: Expected Monthly Return of Portfolio Re (𝜷 Dow) | F38: =G32 + F36 * G33 -> 0.0059705775
F40: Monthly | G40: Annual
E41: Sharpe Ratio with S&P Index | F41: =(F37 - G32) / H25 -> 0.042220792 | G41: =F41 * SQRT(12) -> 0.14625711
E42: Sharpe Ratio with Dow Index | F42: =(F38 - G32) / H25 -> 0.062287409 | G42: =F42 * SQRT(12) -> 0.21576991
E44: Historical Monthly Sharpe Ratio | F44: =AVERAGE('Data Descriptors 1'!BC9:BC43) / 'Statistical Tests'!H25 -> 0.41106921 | G44: =F44 * SQRT(12) -> 1.4239855
E46: Jensen's Alpha (S&P Index) | F46: =I24 - F37 -> 0.016043674 | G46: =((1 + F46) ^12) - 1 -> 0.21045462
E47: Jensen's Alpha (Dow Index) | F47: =I24 - F38 -> 0.015019051 | G47: =((1 + F47) ^12) - 1 -> 0.19588749

Sheet References
